Workbook

Sheet Cover
A1: Oracle Alumni Network Portal - Project Plan (CPMAI)
A2: Cognitive Project Management for AI | Business > Data > Modeling > Evaluation > Deployment > Monitoring
A4: CPMAI Golden Rule: AI Success = Business + Data + Technology + Adoption | Portal Adaptation: Business + Data + Design + Adoption
A6: Document control
A7: Project / Program Name | B7: Oracle Alumni Network Portal - Creation
A8: Client / Organization | B8: Oracle
A9: Executive Sponsor (CXO) | B9: [Executive Sponsor - CXO]
A10: Project Manager | B10: [Project Manager]
A11: Product Owner / Design Lead | B11: [Product Owner / Design Lead]
A12: Source Board | B12: OAN Portal Delivery Board (Plan V3.2, iteration 9, 13 Oct 2026) + APEX Build Pack V1.1 (Q31) + Functional Specification v1.1
A13: Application / Stack | B13: Oracle APEX 26.1.5 on dev (Q32); ORDS; OAN_APP workspace
A14: Plan Scope | B14: 16 sprints S0-S15 - 11 gates - 154 tracked tasks - 319.75 pd (before 20% contingency)
A15: Delivery Window | B15: 19 Oct 2026 (S0) to 28 May 2027 (end S15)
A16: Document Reference | B16: OAN-PLAN-V3.2
A17: Version | B17: 3.2
A18: Status | B18: Baseline for CXO review
... A20: Classification | B20: [Internal / Confidential]
A22: Frameworks applied
A23: CPMAI - Cognitive Project Management for AI (PMI): Business Understanding > Data Understanding > Modeling > Evaluation > Deployment > Monitoring
A24: Spec-Driven Development (SDD): the Functional Specification v1.1 and APEX Build Pack V1.1 are the governing specs; the build follows Build Pack wave order (Q31) with Build Pack page numbers
A25: Delivery board discipline: 16 sprints S0-S15, 11 gates incl. go-live 8.0, 154 tracked tasks, velocity-based capacity with a 20% contingency
A26: Build options are gated: each option (AI assistant, channels, Careers feed) is built in DEV and switched on in PROD only after its DPIA annex and external agreement (G-AI, G-CH, G-CF)
A27: Priority tiers P0-P4 from docs/05-flow-priority.md: P0 and P1 are never cut; the S11 descope lane cuts from P4 upward
A28: Scope decisions applied: no Oracle HR brokering (Q29), no Oracle logos (Q30)
A29: Responsible AI / privacy gate: Legal - Ethical - Secure - Explainable - Valuable (alumni PII, consent and a DPIA per option)
A30: Oracle brand foundations: Oracle Red #C74634 - Ink #201E1C - Charcoal #312D2A - Canvas #FCFBFA
A31: WCAG 2.2 AA accessibility target across all screens and 4 breakpoints
A32: RACI / RASCI accountability, RAID log discipline and an explicit gate checklist
A34: Baseline: OAN Portal Delivery Board, Plan V3.2 / iteration 9 (13 Oct 2026) - 16 sprints S0-S15, 11 gates, 154 tracked tasks, 319.75 pd. Governing specs: Functional Specification v1.1 and APEX Build Pack V1.1 (Q31). Stack: APEX 26.1.5 on dev (Q32), ORDS. Frameworks: CPMAI (PMI) and Spec-Driven Development.

Sheet ReadMe
A1: ReadMe - How to use this workbook
A2: Purpose, tab guide, CPMAI reference, and the keys and definitions used throughout.
A4: Purpose | B4: This workbook is the single planning and governance control point for the Oracle Alumni Network Portal. It is aligned to the OAN Portal Delivery Board (Plan V3.2, iteration 9, 13 Oct 2026): 16 sprints S0-S15, 11 gates including go-live 8.0, 154 tracked tasks and 319.75 pd of development estimate before the 20% contingency.
A5: How to use | B5: 1) Confirm the Delivery Board and Gate Checklist. 2) Work the Kanban Board sprint by sprint. 3) Close each gate before the next stage. 4) Plan capacity on the Sprint Capacity Planner and log actuals weekly. 5) Review RAID weekly. 6) Report value at the Steering Committee using the KPI Dashboard.
A6: Sprint cadence | B6: Setup and design run in S0 (19-30 Oct 2026); build runs S1-S11 in Build Pack wave order (Q31); S12-S13 cover hardening, UAT, go-live; S14-S15 cover the pilot, hypercare and handover. Capacity per sprint is planned on the Sprint Capacity Planner and every closed sprint is logged on the Sprint Performance Tracker.
A7: Update cadence | B7: Plan and board: weekly and at every gate. Sprint Performance Tracker: at each sprint close. Gate Checklist: per gate. KPI Dashboard and Success Plan: monthly. RAID Log: weekly. Artefact Register: on every artefact version change.
A8: Golden Rule | B8: CPMAI Golden Rule: AI Success = Business + Data + Technology + Adoption | Portal Adaptation: Business + Data + Design + Adoption
A9: Source of truth | B9: The attached OAN Portal Delivery Board defines the plan baseline: S0 19-30 Oct 2026 to S15 17-28 May 2027, 11 gates (G0, G1, G-RB, G-AI, G-CH, G-CF, G2, G3, G4, G5, 8.0), 154 tracked tasks and 319.75 pd. Card status comes from task_plan.md in the GitHub repository.
A11: Tab guide
A12: Tab | B12: What it is for | C12: Owner
A13: Cover | B13: Document control, the plan baseline and the frameworks applied. | C13: PM
A14: ReadMe | B14: Purpose, tab guide, CPMAI reference, keys and definitions. | C14: PM
A15: Lifecycle Roadmap | B15: The CPMAI phases mapped to the 16 sprints S0-S15 and the 11 board gates. | C15: PM / Product Owner
A16: Setup & Design Plan | B16: Setup and design work inside the S0-S1 window (19 Oct - 13 Nov 2026), feeding gate G0. | C16: PM
A17: CXO Governance | B17: Governance bodies, decision rights, cadence, escalation and the CXO decision log. | C17: Executive Sponsor
A18: Success Plan | B18: Goals and measures of success, success criteria, adoption plan and benefits realisation. | C18: Product Owner
A19: Change & Adoption | B19: Change strategy, stakeholder analysis, impact assessment, comms plan, training plan and ADKAR readiness tracker. | C19: Change & Comms Lead
A20: Value Stream Map | B20: As-is alumni engagement value stream, flow efficiency, pain points and opportunities by stage. | C20: UX Lead / Product Owner
A21: KPI Dashboard | B21: Reconnect, re-engage, re-hire, self-serve, quality, delivery and board-delivery KPIs with baselines and targets. | C21: Product Owner
A22: RACI Matrix | B22: Accountability for every activity across all roles, including the sprint and gate activities. | C22: PM
A23: RAID Log | B23: Risks, Assumptions, Issues and Dependencies aligned to the board - G0 blockers, gated options, descope lane. | C23: PM / Risk Owner
... A42: CI-CD Pipeline | B42: The four pipeline stages, the pipeline items and their state, and the manual dev deploy. | C42: DevOps / Delivery Lead
A44: CPMAI lifecycle - quick reference
A45: # | B45: CPMAI Phase | C45: Core Question | D45: What it means
A46: 1 | B46: Business Understanding | C46: Why are we doing this? | D46: Anchor the portal to Reconnect, Re-engage, Re-hire and Self-serve; scope confirmed at G1 (end S2).
A47: 2 | B47: Data Understanding | C47: Do we have usable data? | D47: Alumni profile data, directory fields, content library, privacy and consent; re-baselined at G-RB (end S2).
A48: 3 | B48: Modeling | C48: Can we build it? | D48: Design system, 8 core screens and prototype in S0, then Build Pack waves W0-W5 across S1-S7, with gated options at G-AI, G-CH and G-CF.
A49: 4 | B49: Evaluation | C49: Does it work well enough? | D49: Usability test with 5 alumni (FR-34), load test, WCAG 2.2 AA audit, security test and full UAT across S8-S12; signed at G4 and G5.
A50: 5 | B50: Deployment | C50: Will people actually use it? | D50: PROD provision and release in S13, after the 18-check go-live gate 8.0.
A51: 6 | B51: Monitoring | C51: Is it still creating value? | D51: Pilot with ~50 members and every staff role in S14, then two weeks of hypercare and handover in S15.
A53: RACI key (RASCI)
A54: Code | B54: Role | C54: Meaning
A55: R | B55: Responsible | C55: Does the work. At least one per activity.
A56: A | B56: Accountable | C56: Owns the outcome and the final decision. Exactly one per activity.
A57: C | B57: Consulted | C57: Provides input before the work is finalised (two-way).
A58: I | B58: Informed | C58: Kept up to date on progress or decisions (one-way).
A59: S | B59: Support | C59: Assists or provides resources to the Responsible party (RASCI extension).
A61: RAG status key
A62: Code | B62: Status | C62: Meaning
A63: G | B63: Green | C63: On track - no action required.
A64: A | B64: Amber | C64: At risk - corrective action defined and being executed.
A65: R | B65: Red | C65: Off track - escalation required to the Steering Committee.
A67: RAID key
A68: Code | B68: Type | C68: Meaning
A69: R | B69: Risk | C69: A future event that may occur and would harm the project. Has probability and impact.
A70: A | B70: Assumption | C70: Something taken as true without proof; must be validated or it becomes a risk.
A71: I | B71: Issue | C71: A problem that has already occurred and needs resolution now.
A72: D | B72: Dependency | C72: An external deliverable, decision or event the project relies on.

Sheet Lifecycle Roadmap
A1: CPMAI Lifecycle Roadmap - Oracle Alumni Network Portal
A2: The CPMAI phases mapped to the 16 sprints S0-S15 and the 11 board gates. Each phase answers one question and must clear its exit criteria before the next begins.
A4: Phase # | B4: CPMAI Phase | C4: Core Question | D4: Objective | E4: Key Activities | F4: Key Deliverable / Gate | G4: Exit Criteria | H4: Duration (wks) | I4: Accountable | J4: Governance Touchpoint
A5: 0 | B5: Setup & Mobilisation - S0 (19-30 Oct 2026) | C5: Is the toolchain and team ready? | D5: Stand up the toolchain, close the G0 blockers and confirm governance, funding and staffing. | E5: Node, JDK 21 and SQLcl toolchain; dev ADB on APEX 26.1.5 (Q32); ADMIN bootstrap; OIDC client; workspace probe; secrets register; spike results. | F5: G0 - Setup gate (end S0) | G5: Toolchain validated; dev ADB and workspace OAN_APP ready; ADMIN bootstrap run; G0 open items closed. | H5: 2 | I5: PM / Delivery Lead | J5: Steering Committee (S0 review)
A6: 1 | B6: Business Understanding - S0 to S2 | C6: Why are we doing this? | D6: Anchor the portal to Reconnect, Re-engage, Re-hire and Self-serve, and sign off scope and acceptance criteria. | E6: Content inventory and owner; scope and Must/Should/Could baseline; IA and navigation; privacy approach; traceability tagging. | F6: G1 - Scope and AC sign-off (end S2) | G6: Product owner signs off the Must/Should/Could AC list; content owner named. | H6: 4-6 | I6: Product Owner | J6: Steering Committee + Privacy & Compliance Board
A7: 2 | B7: Data Understanding - S1 to S2 | C7: Do we have usable data? | D7: Land the database baseline, confirm data sources and privacy, then re-baseline velocity. | E7: DDL across identity, profile, chapters, content and ops; personal-data registry; seed reference data; audit and visibility; directory index; utPLSQL suites. | F7: G-RB - Re-baseline (end S2) | G7: Measured S1-S2 velocity and offline-rework actuals compared to plan; descope lane invoked if < 20 pd per sprint. | H7: 4 | I7: Data / Privacy Officer | J7: Privacy & Compliance Board + PMO stand-up
A8: 3 | B8: Modeling - S1 to S7 (Build Pack waves W0-W5) | C8: Can we build it? | D8: Build the design system and interface in Build Pack wave order with Build Pack page numbers (Q31). | E8: W0 auth and admin; W1 shell and Home; W2 profile, directory, CV and work profile; W3 content and events; W4 messaging and channels; W5 jobs, helpdesk and organisations. | F8: G-AI (end S3), G-CH (end S6), G-CF (end S7) | G8: Each gated option passes its DPIA annex and external agreement before it is switched on in PROD. | H8: 10-12 | I8: UX Lead / Solution Architect | J8: Design Authority + Compliance Board
A9: 4 | B9: Evaluation - S8 to S12 | C9: Does it work well enough? | D9: Prove usability, accessibility, security, performance and compliance against targets. | E9: Build packs W5-W7; 100k directory smoke test and full load test on temporary ADB; security test (ZAP); WCAG 2.2 AA audit; J-01..J-21 regression; UAT by role. | F9: G2 (end S8), G3 (end S10), G4 and G5 (end S12) | G9: Region decided and load-test ADB booked; staff roles named with 2-step verification; compliance complete; final UAT signed. | H9: 10 | I9: QA Lead / Product Owner | J9: Steering Committee (go / no-go)
A10: 5 | B10: Deployment - S13 (19-30 Apr 2027) | C10: Will people actually use it? | D10: Provision PROD, rehearse the deploy and go live against the 18-check gate. | E10: Provision PROD and rehearsed deploy; seed chapters and attested admins; load legal texts; go-live checklist, rollback and smoke test. | F10: 8.0 - Go-live gate (S13) | G10: All 18 checks pass: DPIA per option, secrets, ORDS exposure and every Must acceptance criterion. | H10: 2 | I10: Delivery / Engineering Lead | J10: Steering Committee + Brand Review Board
A11: 6 | B11: Monitoring - S14 and S15 (and beyond) | C11: Is it still creating value? | D11: Pilot with real members, then hypercare, handover and value tracking. | E11: Pilot with ~50 members, every staff role and >= 3 partner organisations; two weeks of hypercare; handover and v1.x backlog; KPI baseline plan. | F11: Pilot (S14); hypercare and handover (S15) | G11: Pilot validated; exit review kicked off; KPI baseline plan issued for go-live plus 3 months. | H11: 4 + ongoing | I11: Product Owner | J11: Steering Committee (quarterly value review)
A13: Responsible AI gate applies at every phase: Is it Legal? Ethical? Secure? Explainable? Valuable? Without trust there is no scale.

Sheet Setup & Design Plan
A1: Setup & Design Plan - S0 (19-30 Oct 2026) and S1 (2-13 Nov 2026)
A2: Built from the delivery board: the 24 S0 setup tasks (toolchain, spikes, migrations) and the 20 S1 database-baseline tasks. Working days only; 'x' marks the planned working days. S0 closes gate G0; S1 delivers the first shared database deploy and feeds G1 and G-RB.
A4: Board task detail (S0 + S1) | K4: S0 | 19-30 Oct 2026 | L4: S0 | 19-30 Oct 2026 | M4: S0 | 19-30 Oct 2026 | N4: S0 | 19-30 Oct 2026 | O4: S0 | 19-30 Oct 2026 | P4: S0 | 19-30 Oct 2026 | Q4: S0 | 19-30 Oct 2026 | R4: S0 | 19-30 Oct 2026 | S4: S0 | 19-30 Oct 2026 | T4: S0 | 19-30 Oct 2026 | U4: S1 | 2-13 Nov 2026 | V4: S1 | 2-13 Nov 2026 | W4: S1 | 2-13 Nov 2026 | X4: S1 | 2-13 Nov 2026 | Y4: S1 | 2-13 Nov 2026 | Z4: S1 | 2-13 Nov 2026 | AA4: S1 | 2-13 Nov 2026 | AB4: S1 | 2-13 Nov 2026 | AC4: S1 | 2-13 Nov 2026 | AD4: S1 | 2-13 Nov 2026
A5: ID | B5: Sprint | C5: Category | D5: Activity | E5: Owner (R) | F5: Accountable (A) | G5: Dev pd | H5: Priority | I5: Status | J5: Gate | K5: Mon 19 Oct | L5: Tue 20 Oct | M5: Wed 21 Oct | N5: Thu 22 Oct | O5: Fri 23 Oct | P5: Mon 26 Oct | Q5: Tue 27 Oct | R5: Wed 28 Oct | S5: Thu 29 Oct | T5: Fri 30 Oct | U5: Mon 02 Nov | V5: Tue 03 Nov | W5: Wed 04 Nov | X5: Thu 05 Nov | Y5: Fri 06 Nov | Z5: Mon 09 Nov | AA5: Tue 10 Nov | AB5: Wed 11 Nov | AC5: Thu 12 Nov | AD5: Fri 13 Nov
A6: 0.1 | B6: S0 | C6: Environment | D6: Node, JDK 21, SQLcl 26.2 installed | E6: Solution Architect | F6: Solution Architect | G6: 0.5 | H6: P0 | I6: Done | J6: G0 | K6: x
A7: 0.5 | B7: S0 | C7: Environment | D7: Git repo, layout, .gitignore | E7: Solution Architect | F7: Solution Architect | G7: 0.25 | H7: P0 | I7: Done | J7: G0 | K7: x
A8: 0.4 | B8: S0 | C8: Environment | D8: Workspace probe, deployment files, SQLcl connections | E8: Solution Architect | F8: Solution Architect | G8: 0.5 | H8: P0 | I8: Done | J8: G0 | K8: x | L8: x
A9: 0.2 | B9: S0 | C9: Environment | D9: Dev ADB (APEX 26.1.5, Q32), synthetic data | E9: Solution Architect | F9: Solution Architect | G9: 0.5 | H9: P0 | I9: Done | J9: G0 | K9: x | L9: x | M9: x
A10: 0.3 | B10: S0 | C10: Environment | D10: ADMIN bootstrap: schemas, grants, OAN_CTX, sign-in hosts | E10: Solution Architect | F10: Solution Architect | G10: 1.0 | H10: P0 | I10: Done | J10: G0 | L10: x | M10: x | N10: x
A11: 0.10 | B11: S0 | C11: Environment | D11: Spike: APEX version on dev and PROD | E11: Solution Architect | F11: Solution Architect | G11: 0.25 | H11: P0 | I11: Done | J11: G0 | L11: x
A12: 0.15 | B12: S0 | C12: Environment | D12: Secrets register (all secrets, owners, rotation) | E12: Solution Architect | F12: Solution Architect | G12: 1.0 | H12: P0 | I12: In progress | J12: G0 | L12: x | M12: x
A13: 0.9 | B13: S0 | C13: Environment | D13: CI: base-table scan, authz, utPLSQL, gitleaks, validate, page registry, brand | E13: Solution Architect | F13: Solution Architect | G13: 2.5 | H13: P0 | I13: In progress | J13: G0 | M13: x | N13: x | O13: x | P13: x
A14: 0.8 | B14: S0 | C14: Environment | D14: utPLSQL on dev | E14: Solution Architect | F14: Solution Architect | G14: 0.25 | H14: P0 | I14: Done | J14: G0 | N14: x | O14: x
A15: 0.16a | B15: S0 | C15: Environment | D15: Liquibase changelog (forward-only) | E15: Solution Architect | F15: Solution Architect | G15: 1.5 | H15: P0 | I15: Not started | J15: G0 | N15: x | O15: x | P15: x
A16: 0.7 | B16: S0 | C16: Environment | D16: OCI Email Delivery + APEX SMTP | E16: Solution Architect | F16: Solution Architect | G16: 0.5 | H16: P0 | I16: Not started | J16: G0 | P16: x | Q16: x
A17: 0.16b | B17: S0 | C17: Environment | D17: Deploy wrapper + live validate gate | E17: Solution Architect | F17: Solution Architect | G17: 0.75 | H17: P0 | I17: Done | J17: G0 | P17: x | Q17: x
A18: 0.16c | B18: S0 | C18: Environment | D18: Scratch-schema rebuild each sprint | E18: Solution Architect | F18: Solution Architect | G18: 0.5 | H18: P0 | I18: Not started | J18: G0 | Q18: x | R18: x
A19: 0.1b | B19: S0 | C19: Environment | D19: Local Oracle DB Free + utPLSQL (optional) | E19: Solution Architect | F19: Solution Architect | G19: 1.0 | H19: P4 | I19: Not started | J19: G0 | S19: x | T19: x
A20: 0.18 | B20: S0 | C20: Environment | D20: Spike: APEX GenAI service | E20: Solution Architect | F20: Solution Architect | G20: 0.5 | H20: P4 | I20: Not started | J20: G0 | S20: x
A21: 0.19 | B21: S0 | C21: Environment | D21: Procure Slack app, WhatsApp Business | E21: Solution Architect | F21: Solution Architect | G21: OAN | H21: P4 | I21: Not started | J21: G0 | O21: x | P21: x | Q21: x | R21: x | S21: x | T21: x
A22: 0.6 | B22: S0 | C22: Environment | D22: Google OIDC client | E22: Solution Architect | F22: Solution Architect | G22: 0.5 | H22: P0 | I22: Blocked | J22: G0 | M22: x | N22: x
A23: 0.11 | B23: S0 | C23: Environment | D23: Spike: two-schema calls incl. ORDS | E23: Solution Architect | F23: Solution Architect | G23: 1.0 | H23: P0 | I23: Done | J23: G0 | O23: x | P23: x
A24: 0.12 | B24: S0 | C24: Environment | D24: Spike: social sign-in, switch in session, re-auth | E24: Solution Architect | F24: Solution Architect | G24: 1.0 | H24: P0 | I24: Blocked | J24: G0 | O24: x | P24: x
A25: 0.13 | B25: S0 | C25: Environment | D25: Spike: PBKDF2 210k under load | E25: Solution Architect | F25: Solution Architect | G25: 0.5 | H25: P0 | I25: Done | J25: G0 | Q25: x
A26: 0.14 | B26: S0 | C26: Environment | D26: Spike: Oracle Text on ADB | E26: Solution Architect | F26: Solution Architect | G26: 0.5 | H26: P0 | I26: Done | J26: G0 | Q26: x
A27: 0.17 | B27: S0 | C27: Environment | D27: Spike: webhook HMAC + async job < 1s | E27: Solution Architect | F27: Solution Architect | G27: 1.5 | H27: P4 | I27: Blocked | J27: G0 | R27: x | S27: x
A28: M.2 | B28: S0 | C28: Migration | D28: Groups refactor: forums -> groups / posts / comments | E28: Solution Architect | F28: Solution Architect | G28: 3.5 | H28: P1 | I28: Authored offline (validated, not live) | J28: G0 | R28: x | S28: x | T28: x
A29: M.1 | B29: S0 | C29: Migration | D29: APEXLang 26.1 -> 26.2 metadata | E29: Solution Architect | F29: Solution Architect | G29: 1.5 | H29: P0 | I29: Not started | J29: G0 | S29: x | T29: x
A30: 1.1-1.5 | B30: S1 | C30: Database | D30: DDL: identity, profile, chapters, content, ops | E30: Solution Architect | F30: Solution Architect | G30: 7.25 | H30: P0 | I30: Done | J30: G1 / G-RB | U30: x | V30: x
A31: 1.6 | B31: S1 | C31: Database | D31: Personal-data registry + test | E31: Solution Architect | F31: Solution Architect | G31: 0.75 | H31: P0 | I31: Done | J31: G1 / G-RB | V31: x
A32: 1.7 | B32: S1 | C32: Database | D32: Seed reference data | E32: Solution Architect | F32: Solution Architect | G32: 2.0 | H32: P0 | I32: Done | J32: G1 / G-RB | V32: x | W32: x
A33: 1.8-1.13 | B33: S1 | C33: Database | D33: Audit, context, visibility macro, views, security, auth packages | E33: Solution Architect | F33: Solution Architect | G33: 10.75 | H33: P0 | I33: Done | J33: G1 / G-RB | U33: x | V33: x | W33: x
A34: 1.14-1.22 | B34: S1 | C34: Database | D34: Registration, profile, taxonomy, library, files, groups, moderation, notify, privacy | E34: Solution Architect | F34: Solution Architect | G34: 15.0 | H34: P0 | I34: Done | J34: G1 / G-RB | W34: x | X34: x | Y34: x
A35: 1.23 | B35: S1 | C35: Database | D35: Jobs package (fix failure link -> 1075) | E35: Solution Architect | F35: Solution Architect | G35: 1.5 | H35: P0 | I35: In progress | J35: G1 / G-RB | X35: x
A36: 1.24 | B36: S1 | C36: Database | D36: Text/search split (search_body, directory index) | E36: Solution Architect | F36: Solution Architect | G36: 2.0 | H36: P1 | I36: Done | J36: G1 / G-RB | X36: x | Y36: x
A37: 1.25 | B37: S1 | C37: Database | D37: Grants from manifest, synonyms, no-table-grant assert | E37: Solution Architect | F37: Solution Architect | G37: 0.5 | H37: P0 | I37: Done | J37: G1 / G-RB | Y37: x
A38: 1.26 | B38: S1 | C38: Database | D38: utPLSQL suites (R01, R16, R19/20, R26, secrets) | E38: Solution Architect | F38: Solution Architect | G38: 4.0 | H38: P0 | I38: In progress | J38: G1 / G-RB | Y38: x | Z38: x
A39: 1.27 | B39: S1 | C39: Database | D39: Throttle package | E39: Solution Architect | F39: Solution Architect | G39: 1.0 | H39: P0 | I39: Done | J39: G1 / G-RB | Z39: x
A40: 1.29 | B40: S1 | C40: Database | D40: Traceability + Must/Should/Could AC tags (feeds G1) | E40: Solution Architect | F40: Product Owner | G40: 1.5 | H40: P0 | I40: Not started | J40: G1 | Z40: x | AA40: x
A41: 1.30 | B41: S1 | C41: Database | D41: OAN_CTX: ORG/CHANNEL viewer, ROLES, in_group | E41: Solution Architect | F41: Solution Architect | G41: 1.5 | H41: P0 | I41: Done | J41: G1 / G-RB | AA41: x
A42: 1.31 | B42: S1 | C42: Database | D42: Staff scopes + single authz + one grant API | E42: Solution Architect | F42: Solution Architect | G42: 1.5 | H42: P0 | I42: Done | J42: G1 / G-RB | AA42: x | AB42: x
A43: 1.28 | B43: S1 | C43: Database | D43: Synthetic data: 100k profiles, 1M posts, 20k jobs | E43: Solution Architect | F43: Solution Architect | G43: 2.5 | H43: P0 | I43: In progress | J43: G1 / G-RB | AA43: x | AB43: x
A44: 1.32 | B44: S1 | C44: Database | D44: OAN_LU_CODE intents with live_yn (J01-J21 + roles) | E44: Solution Architect | F44: Product Owner | G44: 0.5 | H44: P1 | I44: Authored offline (validated, not live) | J44: G1 | AB44: x
A45: 1.33 | B45: S1 | C45: Database | D45: Retention rules + injectable clock | E45: Solution Architect | F45: Solution Architect | G45: 1.0 | H45: P0 | I45: Done | J45: G1 / G-RB | AB45: x
A46: 1.34 | B46: S1 | C46: Database | D46: Automations map, DBMS_LOCK run locks, send state machine | E46: Solution Architect | F46: Solution Architect | G46: 1.5 | H46: P0 | I46: Done | J46: G1 / G-RB | AC46: x
A47: 1.35 | B47: S1 | C47: Database | D47: Messaging permission, referral opt-in, directory switch | E47: Solution Architect | F47: Product Owner | G47: 0.5 | H47: P1 | I47: Done | J47: G1 / G-RB | AC47: x
A48: 1.36 | B48: S1 | C48: Database | D48: oan_export_pkg (person-level exports) | E48: Solution Architect | F48: Solution Architect | G48: 1.0 | H48: P0 | I48: Done | J48: G1 / G-RB | AC48: x | AD48: x
A49: 1.37 | B49: S1 | C49: Database | D49: option_live(): Build Option + DPIA sign-off | E49: Solution Architect | F49: Product Owner | G49: 0.75 | H49: P0 | I49: Done | J49: G1 / G-RB | AD49: x
A51: - S0 runs 19-30 Oct 2026 (10 working days) and closes gate G0; S1 runs 2-13 Nov 2026 and delivers the first shared database deploy (db-baseline-v1), feeding G1 and the G-RB re-baseline.
A52: - Board totals: S0 = 21 tracked tasks, 18.75 pd; S1 = 17 tracked tasks, 49.25 pd. Estimates are developer person-days before the 20% contingency.
A53: - Three S0 cards are Blocked on G0 decisions: 0.6 Google OIDC client, 0.12 social sign-in (Google sign-in set aside, Q33) and the staffing decision. 11 of 24 S0 cards are already Done and 15 of 20 S1 cards are Done, so the offline-authored database work is landing ahead of the sprint plan.
A54: - Tiers P0-P4 come from docs/05-flow-priority.md: P0 and P1 are never cut; the S11 descope lane cuts from P4 upward.
A55: - Day shading shows the planned working days within the S0-S1 window; exact daily scheduling is agreed at sprint planning.

Sheet CXO Governance
A1: CXO Governance - Tracking and Decision Rights
A2: Who decides what, how often, and how it escalates. Governance is where AI initiatives are steered, not just reported.
A4: Governance bodies
A5: Governance Body | B5: Purpose / Decision Rights | C5: Chair | D5: Members (Roles) | E5: Cadence | F5: Inputs | G5: Outputs / Decisions | H5: Escalation Path | I5: Status
A6: Executive Steering Committee (CXO) | B6: Owns the business outcome. Approves charter, funding, v1 scope, design sign-off and go/no-go to build. | C6: Executive Sponsor (CXO) | D6: CXO sponsor, Product Owner, PM, Brand, HR/Talent, Marketing, Finance, Legal | E6: Bi-weekly (weekly during gates) | F6: Status report, KPI dashboard, RAID highlights, gate pack | G6: Charter, budget, scope and gate decisions, escalations resolved | H6: To Board / CEO for enterprise-level decisions | I6: Active
A7: Design Authority / Brand Review Board | B7: Protects Oracle brand and design-system integrity across all 8 screens and components. | C7: Brand Review Lead | D7: Design Systems Lead, UX Lead, Marketing, Brand | E7: Weekly during Modeling | F7: Functional Specification v1.1, tokens, component library, screen designs | G7: Brand and design approvals, standards | H7: To Steering Committee | I7: Active
A8: Privacy & Compliance Board | B8: Owns alumni PII, consent, directory visibility and data-protection compliance. | C8: Privacy Officer | D8: Legal, Security, Data Steward, Product Owner | E8: At each gate + on demand | F8: Privacy screen, data model, consent model | G8: Consent and privacy approvals | H8: To Steering Committee if a release is blocked | I8: Active
A9: Accessibility & Quality Board | B9: Ensures WCAG 2.2 AA across breakpoints and a quality bar for the delivered experience. | C9: Accessibility Lead | D9: UX, QA, Front-end Lead, Brand | E9: Bi-weekly | F9: Accessibility spec, audit findings, QA results | G9: Accessibility pass, quality decisions | H9: To Steering Committee | I9: Active
A10: Product / Content Council | B10: Prioritises screens, content and the roadmap; validates adoption and value. | C10: Product Owner | D10: UX Lead, Content Strategist, Marketing, Business, HR | E10: Weekly | F10: Roadmap, backlog, content plan, adoption metrics | G10: Prioritised backlog, content decisions | H10: To Steering Committee | I10: Active
A11: Architecture & Data Council | B11: Approves the technical architecture, integrations, data contracts and the design-token export. | C11: Solution Architect | D11: Front-end Lead, Back-end Lead, Data Steward, Security | E11: Bi-weekly + on demand | F11: Architecture decisions, data model, integration map | G11: Architecture and data approvals | H11: To Steering Committee | I11: Active
A12: Delivery / PMO Stand-up | B12: Runs day-to-day delivery, tracks the plan, RAID and dependencies. | C12: Project Manager | D12: Workstream leads, UX, Engineering, QA, Content | E12: Daily / weekly | F12: Plan, RAID, burndown, blockers | G12: Delivery status, blocker resolution | H12: To Steering Committee / Product Council | I12: Active
A14: CXO decision log
A15: Decision ID | B15: Date | C15: Decision | D15: Decided By | E15: Rationale | F15: Impact | G15: Status
A16: D-001 | B16: [date] | C16: Approve project charter and funding | D16: Executive Steering Committee | E16: Goals and measures of success agreed | F16: Project mobilised | G16: Approved
A17: D-002 | B17: [date] | C17: Confirm v1 scope - 8 screens, admin/CMS and native apps out of scope | D17: Steering Committee + Product Council | E17: Functional Specification v1.1 scope | F17: Scope baselined | G17: Approved
A18: D-003 | B18: [date] | C18: Approve directory-visibility default (opt-in vs opt-out) | D18: Privacy & Compliance Board | E18: Alumni privacy and consent | F18: Consent model fixed | G18: Pending
A19: D-004 | B19: [date] | C19: Oracle Sans web licence for the alumni domain | D19: Steering Committee | E19: Brand typeface vs. open fallback | F19: Typeface for build fixed | G19: Pending
A20: D-005 | B20: [date] | C20: Event registration in-portal vs. email | D20: Product Council | E20: Reference uses email; portal can register | F20: Events scope fixed | G20: Pending
A21: D-006 | B21: [date] | C21: Gate 4 design sign-off / go to build | D21: Executive Steering Committee | E21: Usability and accessibility results vs. targets | F21: Build authorised | G21: Pending
A22: D-007 | B22: 2026-10-13 | C22: Approve Plan V3.2: 16 sprints S0-S15, 11 gates, merged FSD scope built in Build Pack wave order | D22: Executive Steering Committee | E22: Delivery board baseline, iteration 9 | F22: Delivery sequence baselined | G22: Approved
A23: D-008 | B23: 2026-10-13 | C23: Q31: build in APEX Build Pack wave order using Build Pack page numbers | D23: Product Council | E23: Keeps the build sequence aligned to the pack | F23: Page numbering and build order fixed | G23: Approved
A24: D-009 | B24: 2026-10-13 | C24: Q32: dev runs APEX 26.1.5 (accepted); PROD APEX version policy remains open | D24: Solution Architect / Steering | E24: Dev ADB aiatp accepted on 26.1.5 | F24: M.1 APEXLang 26.1 to 26.2 migration deferred on dev | G24: Approved (dev)
A25: D-010 | B25: 2026-10-13 | C25: Q29: no Oracle HR brokering - HR documents are signposted only | D25: Privacy & Compliance Board | E25: Avoids HR data processing in the portal | F25: Helpdesk scope reduced to signposting | G25: Approved
A26: D-011 | B26: 2026-10-13 | C26: Q30: no Oracle logos on the portal | D26: Brand Review Board | E26: Brand governance | F26: Brand expression limited to palette, type and layout | G26: Approved
A27: D-012 | B27: 2026-10-13 | C27: PROD region selection | D27: Executive Steering Committee | E27: Required before the temporary 100k load-test ADB can be booked | F27: G2 (end S8) depends on this decision | G27: Pending
A29: Escalation path
A30: Level 1 - Project Manager resolves within the delivery team (48 hours).
A31: Level 2 - AI Product Owner / Product Council resolves cross-team issues (weekly).
A32: Level 3 - Steering Committee resolves scope, budget, risk and gate decisions (bi-weekly).
A33: Level 4 - Executive Sponsor / Board resolves enterprise-level or cross-portfolio decisions (as required).

Sheet Change & Adoption
A1: Change Management & Adoption Plan - Oracle Alumni Network Portal
A2: Change is not an afterthought - readiness is built from week 1. ADKAR-based: Awareness > Desire > Knowledge > Ability > Reinforcement.
A4: A. Change strategy
A5: Case for change | C5: Alumni currently reconnect and request documents through fragmented email and third-party sites. The portal gives them one authenticated home - reducing support effort and re-opening the talent pipeline.
A6: Vision | C6: Every Oracle alumnus has a single, trusted place to reconnect, re-engage, return and self-serve.
A7: Change principles | C7: Alumni-first; opt-in and privacy-respecting; gradual habit change over forced migration; champions lead peers; measure readiness, not just go-live.
A8: Approach | C8: ADKAR-based readiness (Awareness > Desire > Knowledge > Ability > Reinforcement) with comms, training, champions and reinforcement from week 1, not after launch.
A9: What success looks like | C9: Alumni choose the portal voluntarily: sign up, complete profiles, return monthly, message peers, register for events and self-serve documents.
A11: B. Stakeholder analysis
A12: Stakeholder / Group | B12: Type | C12: Interest | D12: Influence | E12: Current State | F12: Desired State | G12: Engagement Approach | H12: Owner
A13: Alumni (all members) | B13: End user | C13: High | D13: Medium | E13: Unaware | F13: Aware and active | G13: Launch comms, portal, social, reminders | H13: Change & Comms Lead
A14: Alumni champions (per region) | B14: Advocate | C14: High | D14: High | E14: Unaware | F14: Engaged and advocating | G14: 1:1 briefing, champion toolkit, community | H14: Change & Comms Lead
A15: HR / Talent | B15: Beneficiary | C15: High | D15: High | E15: Supportive | F15: Embedded (boomerang pipeline) | G15: Joint workshops, process update | H15: HR / Talent Lead
A16: Marketing / Communications | B16: Delivery partner | C16: High | D16: Medium | E16: Supportive | F16: Co-delivering launch | G16: Joint comms plan, content cadence | H16: Marketing Lead
A17: Support / Helpdesk | B17: Impacted team | C17: High | D17: Medium | E17: Neutral | F17: Trained and confident | G17: Training, FAQs, operational readiness | H17: Support Lead
A18: Brand / Design Authority | B18: Gatekeeper | C18: Medium | D18: High | E18: Supportive | F18: Approved and aligned | G18: Reviews at each gate | H18: Brand Review Lead
A19: Legal / Privacy | B19: Gatekeeper | C19: Medium | D19: High | E19: Cautious | F19: Compliant and assured | G19: Review packs, consent model sign-off | H19: Privacy Officer
A20: IT / Security | B20: Enabler | C20: Medium | D20: High | E20: Supportive | F20: Aligned | G20: Architecture and security reviews | H20: Solution Architect
A21: CXO / Steering Committee | B21: Sponsor | C21: Medium | D21: High | E21: Supportive | F21: Active sponsor | G21: Steering cadence, value reviews | H21: Executive Sponsor
A23: C. Change impact assessment
A24: Area | B24: Who Is Impacted | C24: What Changes | D24: Impact Level | E24: Mitigation / Enablement | F24: Owner
A25: Onboarding & sign-up | B25: All alumni | C25: Registration and identity verification replace informal access | D25: Medium | E25: Clear comms, one-step verified sign-up, support FAQ | F25: Change & Comms Lead
A26: Profile completion | B26: All alumni | C26: Alumni must add role history and current details | D26: Medium | E26: Completion meter, nudges, smart defaults, explain the value | F26: Product Owner
A27: Directory visibility | B27: All alumni | C27: New privacy setting controls who can find them | D27: High | E27: Explicit consent, safe default, plain-language explanation | F27: Privacy Officer
A28: Engagement habit | B28: All alumni | C28: Return visits replace one-off contact | D28: High | E28: Content cadence, notifications, event programme, champions | F28: Marketing Lead
A29: Document requests | B29: Alumni + Support | C29: Email back-and-forth becomes self-serve form | D29: Medium | E29: Comms, training, in-portal guidance, support fallback | F29: Support Lead
A30: Support operations | B30: Helpdesk team | C30: New tooling, new request types, new SLAs | D30: Medium | E30: Training, runbook, hypercare | F30: Support Lead
A31: Talent pipeline | B31: HR / Talent | C31: Boomerang applications arrive via the portal | D31: Medium | E31: Process update, briefing, referral tracking | F31: HR / Talent Lead
A32: Comms channel | B32: Marketing | C32: A new always-on alumni channel to feed | D32: Low | E32: Briefing, content calendar, ownership agreed | F32: Marketing Lead
A34: D. Communication plan
A35: Audience | B35: Key Message | C35: Channel | D35: Owner | E35: Timing | F35: Frequency
A36: Invited alumni | B36: The portal is live - reconnect with your Oracle network | C36: Email, social, portal | D36: Change & Comms Lead | E36: Week 4 / launch | F36: Once + 2 reminders
A37: Registered alumni | B37: What's new - insights, events and your network | C37: In-portal feed, email | D37: Content Strategist | E37: From launch | F37: Weekly
A38: Alumni champions | B38: Champion programme briefing and toolkit | C38: 1:1 / community call | D38: Change & Comms Lead | E38: Week 3 | F38: Monthly
A39: HR / Talent | B39: Boomerang pipeline now runs through the portal | C39: Email + workshop | D39: HR / Talent Lead | E39: Week 3 | F39: Once
A40: Support / Helpdesk | B40: Operational readiness and new request handling | C40: Training + runbook | D40: Support Lead | E40: Week 4 | F40: Once
A41: CXO / Steering Committee | B41: Adoption and value progress | C41: Steering pack | D41: Product Owner | E41: Bi-weekly | F41: Recurring
A42: Legal / Privacy | B42: Compliance and consent status | C42: Review pack | D42: Privacy Officer | E42: At each gate | F42: Per gate
A43: Wider Oracle staff | B43: Support our alumni - share the portal | C43: Intranet | D43: Change & Comms Lead | E43: Launch | F43: Once
A45: E. Training & enablement plan
A46: Audience | B46: What They Learn | C46: Format | D46: Owner | E46: Timing | F46: Completion Target
A47: All alumni | B47: Sign up, complete profile, find people, message, events | C47: Job aid + short video | D47: Change & Comms Lead | E47: Week 4 to launch | F47: 100% reach
A48: Alumni champions | B48: Champion toolkit, talking points, how to help peers | C48: Workshop | D48: Change & Comms Lead | E48: Week 3 | F48: 100% of champions
A49: Support / Helpdesk | B49: Request handling, FAQs, escalation paths | C49: Instructor-led training | D49: Support Lead | E49: Week 4 | F49: 100% of agents
A50: HR / Talent | B50: Careers and boomerang process in the portal | C50: Briefing | D50: HR / Talent Lead | E50: Week 3 | F50: 100% of team
A51: Content team | B51: Publishing, moderation and the content calendar | C51: Workshop | D51: Content Strategist | E51: Week 4 | F51: 100% of team
A52: Administrators | B52: Admin / CMS console - deferred from v1 | C52: n/a (out of scope v1) | D52: Product Owner | E52: Post v1 | F52: Deferred
A54: F. ADKAR readiness tracker
A55: ADKAR Element | B55: What It Means Here | C55: Key Actions | D55: Readiness Measure | E55: Owner | F55: Status
A56: A - Awareness | B56: Alumni understand why the portal exists and what it offers | C56: Launch comms, leadership letter, social | D56: Comms reach / awareness | E56: Change & Comms Lead | F56: Not started
A57: D - Desire | B57: Alumni want to join and take part | C57: Champions, peer stories, clear value | D57: Sign-up intent survey | E57: Change & Comms Lead | F57: Not started
A58: K - Knowledge | B58: Alumni know how to use the portal | C58: Training assets, job aids, onboarding | D58: Training reach | E58: Change & Comms Lead | F58: Not started
A59: A - Ability | B59: Alumni can complete key tasks unaided | C59: Usability fixes, empty states, support | D59: Usability task success | E59: UX Lead | F59: Not started
A60: R - Reinforcement | B60: New habits and value are sustained after launch | C60: Content cadence, notifications, value reports | D60: Monthly return visits | E60: Marketing Lead | F60: Not started
A62: G. Change KPIs (also on the KPI Dashboard)
A63: KPI ID | B63: KPI | C63: Definition / Formula | D63: Baseline | E63: Target | F63: Owner | G63: Frequency
A64: CK-01 | B64: Change readiness score | C64: avg ADKAR readiness across audiences | D64: [baseline] | E64: >= 80% | F64: Change & Comms Lead | G64: Weekly from week 3
A65: CK-02 | B65: Comms reach / awareness | C65: alumni who saw launch comms / invited | D65: 0% | E65: >= 80% | F65: Change & Comms Lead | G65: Launch + 2 weeks
A66: CK-03 | B66: Training completion | C66: target audience trained / total target | D66: 0% | E66: >= 90% | F66: Change & Comms Lead | G66: By launch
A67: CK-04 | B67: Champion coverage | C67: regions or teams with an active champion / total | D67: 0% | E67: >= 80% | F67: Change & Comms Lead | G67: Week 4
A68: CK-05 | B68: Resistance / escalations | C68: count of open high change-resistance items | D68: [baseline] | E68: 0 high | F68: Change & Comms Lead | G68: Weekly

Sheet Success Plan
A1: Success Plan - Definition of Success, Adoption and Benefits
A2: AI success = Business + Data + Technology + Adoption. Success is defined, measured and owned before build begins.
A4: A. Value hypothesis
A5: Problem / opportunity | C5: [Describe the business problem or opportunity in one sentence.]
A6: Proposed agentic solution | C6: [Describe the agent, the workflow it automates and where a human stays in the loop.]
A7: Expected outcome | C7: [Describe the measurable business outcome and the value it creates.]
A8: Why agentic AI | C8: [Explain why an autonomous agent - not a simpler automation - is the right fit.]
A9: Value at stake | C9: [Quantify the annual value at stake, e.g. cost, revenue, risk, experience.]
A11: B. Success criteria
A12: ID | B12: Success Criterion | C12: Category | D12: Metric | E12: Baseline | F12: Target | G12: Measurement Method | H12: Owner | I12: Timeframe
A13: SC-01 | B13: Alumni locate and follow a former colleague quickly | C13: Reconnect | D13: Searches to find a colleague | E13: [baseline] | F13: Within 2 searches | G13: Usability test + search analytics | H13: UX Lead | I13: Gate 4 / post-launch
A14: SC-02 | B14: Alumni return to the portal regularly | C14: Re-engage | D14: Monthly return visits | E14: [baseline] | F14: [target] by month 3 | G14: Web analytics | H14: Product Owner | I14: Month 3 post go-live
A15: SC-03 | B15: Alumni apply to return to Oracle | C15: Re-hire | D15: Boomerang applications via Careers | E15: [baseline] | F15: [target] per quarter | G15: Careers referral tracking | H15: HR / Talent Lead | I15: Quarterly
A16: SC-04 | B16: Document requests are resolved without email back-and-forth | C16: Self-serve | D16: Self-serve resolution rate | E16: [baseline] | F16: >= 70% | G16: Helpdesk request logs | H16: Support Lead | I16: Month 2 post go-live
A17: SC-05 | B17: The portal is usable by real alumni | C17: Usability | D17: Task success rate in usability test | E17: [baseline] | F17: >= 85% | G17: Usability test with 5 alumni | H17: UX Research Lead | I17: Gate 4
A18: SC-06 | B18: The portal is accessible | C18: Accessibility | D18: WCAG 2.2 AA conformance | E18: Not assessed | F18: AA pass, 0 critical | G18: Accessibility audit | H18: Accessibility Lead | I18: Gate 4
A19: SC-07 | B19: The portal is on-brand | C19: Brand | D19: Brand review outcome | E19: n/a | F19: Pass, 0 critical | G19: Design Authority review | H19: Brand Review Lead | I19: Gate 4
A20: SC-08 | B20: Design is ready for build | C20: Delivery | D20: Screens signed off + tokens exported | E20: 0 | F20: 8 of 8 + token export | G20: Handoff checklist | H20: Design Systems Lead | I20: Gate 4
A21: SC-09 | B21: Profiles are complete enough to be useful | C21: Adoption | D21: Average profile completion | E21: 69% (reference) | F21: >= 90% | G21: Profile completion meter | H21: Product Owner | I21: Month 2 post go-live
A22: SC-10 | B22: The board delivers on the gate sequence | C22: Delivery | D22: Gates passed on or before their due date | E22: 0 of 11 | F22: 11 of 11 by S13 | G22: Gate Checklist | H22: Product Owner | I22: S13 (go-live)
A23: SC-11 | B23: Effort stays within the estimate and contingency | C23: Delivery | D23: pd delivered vs the 319.75 pd plan incl. 20% contingency | E23: 0 | F23: Within +/- 10% of plan | G23: Board Tasks + Sprint Performance Tracker | H23: PM | I23: S13 (go-live)
A25: C. Adoption plan
A26: Element | B26: Audience | C26: Action | D26: Owner | E26: Timing | F26: Success Signal
A27: Executive sponsorship | B27: CXO / Steering Committee | C27: Visible sponsorship, gate decisions, value review | D27: Executive Sponsor | E27: Ongoing | F27: Gates attended, decisions made
A28: Alumni communication plan | B28: All alumni | C28: Launch comms, what's new feed, email and social | D28: Change & Comms Lead | E28: From Gate 4 | F28: Awareness and sign-up rate
A29: Profile completion nudges | B29: Registered alumni | C29: In-app completion meter nudges to 100% | D29: Product Owner | E29: From launch | F29: Avg completion >= 90%
A30: Onboarding & first-run | B30: New members | C30: Guided first-run and empty-state guidance | D30: UX Lead | E30: From launch | F30: First-session task completion
A31: Champion network | B31: Alumni leaders / regions | C31: Peer advocacy and event promotion | D31: Change & Comms Lead | E31: From launch | F31: Champions active per region
A32: Content cadence | B32: All members | C32: Regular insights, perspectives and announcements | D32: Content Strategist | E32: Weekly from launch | F32: Return visits driven by content
A33: Events programme | B33: All members | C33: In-portal registration and calendar for events | D33: Marketing Lead | E33: From launch | F33: Registrations per event
A34: Feedback loop | B34: All members | C34: In-app feedback and support routed to the backlog | D34: Product Owner | E34: From launch | F34: Feedback triaged weekly
A35: Value storytelling | B35: CXO + organisation | C35: Publish realised value and lessons | D35: Product Owner | E35: Monthly | F35: Value report issued
A36: Pilot programme | B36: ~50 members, every staff role, >= 3 partner organisations | C36: Run the S14 pilot across all staff roles and partner orgs before hypercare | D36: Product Owner | E36: S14 (3-14 May 2027) | F36: Pilot validated; exit review kicked off
A37: Hypercare and handover | B37: Support, HR, Marketing, Operations | C37: Two weeks of hypercare, then handover and the v1.x backlog | D37: Delivery Lead | E37: S15 (17-28 May 2027) | F37: Handover complete; backlog agreed
A39: D. Benefits realisation
A40: Benefit ID | B40: Benefit | C40: Type | D40: Quantified Value | E40: Baseline | F40: Realisation Date | G40: Owner | H40: Status
A41: B-01 | B41: Reduced support effort for document requests (self-serve) | C41: Cost / productivity | D41: [value] | E41: [baseline] | F41: [date] | G41: Support Lead | H41: Planned
A42: B-02 | B42: Reconnect: alumni network activity and relationships re-established | C42: Engagement | D42: [value] | E42: [baseline] | F42: [date] | G42: Product Owner | H42: Planned
A43: B-03 | B43: Re-engage: increased monthly return visits and content reach | C43: Engagement | D43: [value] | E43: [baseline] | F43: [date] | G43: Marketing Lead | H43: Planned
A44: B-04 | B44: Re-hire: boomerang talent pipeline via Careers | C44: Talent | D44: [value] | E44: [baseline] | F44: [date] | G44: HR / Talent Lead | H44: Planned
A45: B-05 | B45: Reusable Oracle-branded design system for future alumni and talent portals | C45: Strategic | D45: [value] | E45: [baseline] | F45: [date] | G45: Design Systems Lead | H45: Planned
A47: E. Definition of Done
A48: - The agent performs the target task end-to-end at or above the agreed quality threshold.
A49: - Responsible AI controls are in place and approved; audit trail is complete.
A50: - Users are trained, enabled and actively adopting the agent in the real workflow.
A51: - KPIs meet their targets at Gate 4 and continue to hold at the Gate 6 value review.
A52: - Benefits are validated against the baseline and reported to the Steering Committee.

Sheet Value Stream Map
A1: Value Stream Map - As-Is Alumni Engagement Flow
A2: Map the flow from trigger to value. Find the stages where wait time and rework destroy value - that is where agentic AI earns its place.
A4: As-is value stream
A5: Stage # | B5: Stage Name | C5: Entry Trigger | D5: Key Activities | E5: VA / NVA | F5: Lead Time (days) | G5: Process Time (days) | H5: Wait Time (days) | I5: Flow Efficiency | J5: Pain Points | K5: Systems / Data | L5: Opportunity | M5: Target State | N5: Priority
A6: 1 | B6: Discover & sign up | C6: An alumnus hears about the portal | D6: Learn about the portal, register, verify identity | E6: NVA | F6: 3.0 | G6: 0.3 | H6: 2.7 | I6: 10% | J6: Unclear invitation, verification friction, no single entry point | K6: Email, marketing, SSO | L6: Clear invitation and one-step verified sign-up | M6: Frictionless, verified onboarding | N6: High
A7: 2 | B7: Complete profile | C7: Signed up | D7: Add role history, location, current role, photo | E7: VA | F7: 14.0 | G7: 1.0 | H7: 13.0 | I7: 7% | J7: Long form, unclear value, profile stalls at 69% | K7: Profile service | L7: Completion meter, nudges and smart defaults | M7: >= 90% profile completion | N7: High
A8: 3 | B8: Find former colleagues | C8: Wants to reconnect | D8: Search and filter the alumni directory | E8: VA | F8: 2.0 | G8: 0.3 | H8: 1.7 | I8: 15% | J8: Weak filters, poor data, dead ends | K8: Directory, profile data | L8: Strong filters (tenure, line of business, last role) and relevant results | M8: Find within 2 searches | N8: High
A9: 4 | B9: Connect & converse | C9: Found a colleague | D9: Follow, message, join groups | E9: VA | F9: 1.0 | G9: 0.3 | H9: 0.7 | I9: 30% | J9: No messaging in the old experience; email back-and-forth | K9: Conversations service | L9: In-portal 1:1 and group messaging with announcements | M9: In-portal conversation | N9: High
A10: 5 | B10: Engage with insights & events | C10: Portal visit | D10: Read insights, register for events | E10: VA | F10: 2.0 | G10: 0.5 | H10: 1.5 | I10: 25% | J10: Content scattered, event sign-up by email | K10: Content, events | L10: Curated feed and in-portal event registration + calendar | M10: Self-serve engagement | N10: High
A11: 6 | B11: Explore return-to-Oracle | C11: Considering a return | D11: Search Oracle and partner jobs; boomerang programme | E11: VA | F11: 5.0 | G11: 0.5 | H11: 4.5 | I11: 10% | J11: Careers opens a separate site; unclear path back | K11: Careers, HR | L11: Embedded boomerang hero and in-portal job search | M11: Boomerang applications grow | N11: Medium
A12: 7 | B12: Request HR documents | C12: Needs a document | D12: Request payslips, Form-16, relieving letter | E12: VA | F12: 6.0 | G12: 0.3 | H12: 5.7 | I12: 5% | J12: Email back-and-forth, no status, manual handling | K12: Helpdesk, HR | L12: Self-serve request form with consent and reference ID | M12: Resolved without email | N12: High
A13: 8 | B13: Re-engage & return | C13: Time passes | D13: Return visits driven by content, events, network | E13: NVA | F13: 30.0 | G13: 0.5 | H13: 29.5 | I13: 2% | J13: No reason to return; no habit loop | K13: Analytics, content | L13: Regular content cadence, notifications and event programme | M13: Monthly return visits grow | N13: High
A15: Flow summary
A16: Metric | B16: As-Is | C16: Target (To-Be) | D16: Improvement
A17: Total lead time (days) | B17: 63.0 | C17: [target] | D17: [x]
A18: Total process time (days) | B18: 3.7 | C18: [target] | D18: [x]
A19: Total wait time (days) | B19: 59.3 | C19: [target] | D19: [x]
A20: Flow efficiency (process / lead) | B20: 6% | C20: >= 25% | D20: +19 pts
A21: Stages with high-value opportunity | B21: 6 of 8 | C21: 6 of 8 | D21: -
A22: Highest-leverage stages | B22: 2, 3, 4, 7 (Profile, Find, Connect, Self-serve) | C22: Target these first | D22: -
A24: Flow efficiency = process time / lead time. Low efficiency means the work waits more than it works - the prime target for an autonomous agent.

Sheet KPI Dashboard
A1: KPI Dashboard - Measuring What Matters
A2: Business, adoption, data, technology, Responsible AI and delivery KPIs - each with a definition, baseline, target, owner and RAG threshold. Delivery KPIs (cards complete, gate pass rate, effort burn, blocked cards, descope use) are read from the Kanban Dashboard.
A4: KPI ID | B4: Category | C4: KPI | D4: Definition / Formula | E4: Data Source | F4: Frequency | G4: Baseline | H4: Target | I4: Green / Amber / Red | J4: Owner | K4: Linked Criterion | L4: Current Value | M4: RAG
A5: K-01 | B5: Reconnect | C5: Searches to find a colleague | D5: avg searches before a successful follow | E5: Analytics | F5: Weekly | G5: [baseline] | H5: <= 2 | I5: G <=2 / A 3 / R >3 | J5: UX Lead | K5: SC-01
A6: K-02 | B6: Reconnect | C6: Directory search success rate | D6: searches returning a result / total searches | E6: Analytics | F6: Weekly | G6: [baseline] | H6: >= 90% | I6: G >=90 / A 75-89 / R <75 | J6: Product Owner | K6: SC-01
A7: K-03 | B7: Reconnect | C7: Follow / connect rate | D7: members followed / directory visitors | E7: Analytics | F7: Weekly | G7: [baseline] | H7: >= 25% | I7: G >=25 / A 12-24 / R <12 | J7: Product Owner | K7: SC-01
A8: K-04 | B8: Re-engage | C8: Monthly return visits | D8: distinct members returning in a month | E8: Analytics | F8: Monthly | G8: [baseline] | H8: [target] by month 3 | I8: G >=target / A 70-99% / R <70% | J8: Marketing Lead | K8: SC-02
A9: K-05 | B9: Re-engage | C9: Content engagement rate | D9: article reads / active members | E9: Analytics | F9: Monthly | G9: [baseline] | H9: >= 40% | I9: G >=40 / A 20-39 / R <20 | J9: Content Strategist | K9: SC-02
A10: K-06 | B10: Re-engage | C10: Event registrations per event | D10: registrations per published event | E10: Events service | F10: Per event | G10: [baseline] | H10: [target] | I10: G >=target / A 70-99% / R <70% | J10: Marketing Lead | K10: SC-02
A11: K-07 | B11: Re-hire | C11: Boomerang applications | D11: applications via Careers per quarter | E11: Careers / HR | F11: Quarterly | G11: [baseline] | H11: [target] | I11: G >=target / A 70-99% / R <70% | J11: HR / Talent Lead | K11: SC-03
A12: K-08 | B12: Re-hire | C12: Careers engagement | D12: job searches and role views in-portal | E12: Analytics | F12: Monthly | G12: [baseline] | H12: [target] | I12: G >=target / A 70-99% / R <70% | J12: HR / Talent Lead | K12: SC-03
A13: K-09 | B13: Self-serve | C13: Self-serve resolution rate | D13: requests resolved without email / total | E13: Helpdesk logs | F13: Weekly | G13: [baseline] | H13: >= 70% | I13: G >=70 / A 45-69 / R <45 | J13: Support Lead | K13: SC-04
A14: K-10 | B14: Self-serve | C14: Document request turnaround | D14: avg hours from request to resolution | E14: Helpdesk logs | F14: Weekly | G14: [baseline] | H14: <= 48h | I14: G <=48 / A 49-96 / R >96 | J14: Support Lead | K14: SC-04
A15: K-11 | B15: Self-serve | C15: Form completion rate | D15: requests submitted / forms started | E15: Helpdesk logs | F15: Weekly | G15: [baseline] | H15: >= 85% | I15: G >=85 / A 65-84 / R <65 | J15: UX Lead | K15: SC-04
A16: K-12 | B16: Adoption | C16: Registered alumni | D16: verified members / invited alumni | E16: Auth / analytics | F16: Monthly | G16: [baseline] | H16: [target] | I16: G >=target / A 70-99% / R <70% | J16: Change & Comms Lead | K16: SC-02
... A49: K-45 | B49: Delivery | C49: Descope lane use | D49: P4 pd cut at the S11 descope lane | E49: Sprint Capacity Planner | F49: At S11 | G49: 0 pd | H49: <= 10% of P4 pd | I49: G <=10 / A 11-20 / R >20 | J49: Product Owner | K49: SC-11

Sheet RACI Matrix
A1: RACI Matrix - Oracle Alumni Network Portal
A2: R = Responsible | A = Accountable (exactly one) | C = Consulted | I = Informed | S = Support
A4: CPMAI Phase | B4: Activity | C4: Executive Sponsor (CXO) | D4: Steering Committee | E4: Product Owner | F4: Project Manager | G4: UX Lead | H4: UI / Visual Designer | I4: Design Systems Lead | J4: Content Strategist | K4: Front-end Lead | L4: Back-end Lead | M4: Solution Architect | N4: Accessibility Lead | O4: Data / Privacy Officer | P4: Brand Review Lead | Q4: Change & Comms Lead | R4: Scrum Master / Delivery Lead | S4: Integration / Channel Lead
A5: Mobilise | B5: Approve project charter and funding | C5: A | D5: R | E5: C | F5: S | G5: C | I5: C | M5: C | O5: C | P5: C
A6: Mobilise | B6: Stand up governance bodies | C6: A | D6: C | E6: C | F6: R | G6: C | I6: C | J6: C | M6: C | N6: C | O6: C | P6: C | Q6: C
A7: Mobilise | B7: Agree RACI and ways of working | C7: I | D7: I | E7: A | F7: R | G7: C | H7: C | I7: C | J7: C | K7: C | L7: C | M7: C | N7: C | O7: C | P7: C | Q7: C
A8: Business Understanding | B8: Stakeholder review of Functional Specification v1.1 | C8: I | D8: I | E8: R | F8: S | G8: C | H8: C | I8: C | J8: C | M8: C | N8: C | O8: C | P8: C | Q8: C
A9: Business Understanding | B9: Confirm goals and measures of success | C9: A | D9: C | E9: R | F9: S | G9: C | J9: C | O9: C | Q9: C
A10: Business Understanding | B10: Confirm v1 scope (8 screens, in / out) | C10: A | D10: C | E10: R | F10: S | G10: C | I10: C | J10: C | K10: C | L10: C | M10: C
A11: Business Understanding | B11: Validate IA and navigation model | C11: I | D11: I | E11: A | F11: S | G11: R | H11: C | I11: C | J11: C | K11: C | M11: C | N11: C
A12: Business Understanding | B12: Content inventory and copy rules | C12: I | D12: I | E12: A | F12: S | G12: C | H12: C | J12: R | P12: C | Q12: C
A13: Business Understanding | B13: Privacy and consent screening | C13: A | D13: C | E13: C | F13: S | M13: C | O13: R
A14: Business Understanding | B14: Confirm governance cadence | C14: A | D14: C | E14: C | F14: R | G14: C | O14: C | P14: C | Q14: C
A15: Data Understanding | B15: Define alumni data model and directory fields | C15: I | D15: I | E15: C | F15: S | G15: C | J15: C | K15: C | L15: C | M15: A | O15: R
A16: Data Understanding | B16: Confirm data sources and integrations | C16: I | D16: C | E16: C | F16: S | K16: C | L16: R | M16: A | O16: C
A17: Data Understanding | B17: Agree directory-visibility defaults | C17: A | D17: C | E17: C | F17: S | M17: C | N17: C | O17: R
A18: Data Understanding | B18: Resolve open questions (licence, letter, events, regions) | C18: A | D18: C | E18: R | F18: S | I18: C | J18: C | M18: C | O18: C | P18: C | Q18: C
A19: Data Understanding | B19: Finalise design tokens | C19: I | D19: I | E19: C | F19: S | G19: C | H19: C | I19: R | K19: C | M19: C | N19: C | P19: A
A20: Data Understanding | B20: Accessibility spec - WCAG 2.2 AA | C20: I | D20: C | E20: C | F20: S | G20: C | H20: C | I20: C | K20: C | M20: C | N20: R | P20: A
A21: Data Understanding | B21: Responsive breakpoint spec | C21: I | D21: I | E21: C | F21: S | G21: R | H21: C | I21: C | K21: C | M21: C | N21: C | P21: A
A22: Data Understanding | B22: Content and copy rules; data fallbacks | C22: I | D22: I | E22: A | F22: S | G22: C | H22: C | J22: R | P22: C | Q22: C
A23: Modeling | B23: Shape and write screen specs | C23: I | D23: I | E23: A | F23: S | G23: R | H23: C | I23: C | J23: C | K23: C | L23: C | M23: C | N23: C
A24: Modeling | B24: Build component library | C24: I | D24: I | E24: C | F24: S | G24: C | H24: C | I24: R | J24: C | K24: C | N24: C | P24: A
A25: Modeling | B25: Design the 8 core screens | C25: I | D25: I | E25: A | F25: S | G25: C | H25: R | I25: C | J25: C | N25: C | P25: C
A26: Modeling | B26: Build clickable hi-fi prototype | C26: I | D26: I | E26: A | F26: S | G26: R | H26: C | I26: C | N26: C
A27: Modeling | B27: Accessibility review of the prototype | C27: I | D27: C | E27: C | F27: S | G27: C | H27: C | I27: C | K27: C | N27: R | P27: A
A28: Evaluation | B28: Usability test with 5 alumni | C28: I | D28: I | E28: A | F28: S | G28: R | H28: C | J28: C | N28: C | Q28: C
A29: Evaluation | B29: Analyse findings and prioritise fixes | C29: I | D29: I | E29: A | F29: S | G29: R | H29: C | I29: C | J29: C | N29: C
A30: Evaluation | B30: WCAG 2.2 AA audit and remediation | C30: I | D30: C | E30: C | F30: S | G30: C | I30: C | K30: R | L30: C | M30: C | N30: A | P30: C
A31: Evaluation | B31: Brand compliance and quality review | C31: I | D31: C | E31: C | F31: S | G31: C | H31: C | I31: C | J31: C | N31: C | P31: R
A32: Evaluation | B32: Stakeholder review and design sign-off | C32: A | D32: R | E32: C | F32: S | G32: C | I32: C | J32: C | P32: C
A33: Evaluation | B33: Dev handoff and token export | C33: I | D33: I | E33: C | F33: S | G33: C | H33: C | I33: R | K33: C | L33: C | M33: C | N33: C
A34: Evaluation | B34: Go / No-Go decision to build | C34: A | D34: R | E34: C | F34: S | G34: C | I34: C | K34: C | L34: C | M34: C | N34: C | O34: C | P34: C | Q34: C
A35: Deployment | B35: Front-end and back-end build | C35: I | D35: C | E35: C | F35: S | G35: C | H35: C | I35: C | K35: R | L35: R | M35: C | N35: C
A36: Deployment | B36: Integration, QA and launch | C36: I | D36: C | E36: A | F36: R | G36: C | I36: C | K36: R | L36: R | M36: C | N36: C | O36: C | Q36: C
A37: Deployment | B37: Alumni onboarding and launch comms | C37: I | D37: I | E37: A | F37: S | G37: C | J37: C | O37: C | Q37: R
A38: Monitoring | B38: Monitor adoption, engagement and quality | C38: I | D38: C | E38: A | F38: S | G38: C | I38: C | J38: C | K38: C | L38: C | M38: C | N38: C | O38: C | Q38: C
A39: Monitoring | B39: Track benefits realisation and value | C39: A | D39: C | E39: R | F39: S | G39: C | J39: C | O39: C | Q39: C
A40: Monitoring | B40: Run continuous improvement backlog | C40: I | D40: I | E40: A | F40: S | G40: C | H40: C | I40: C | J40: C | K40: C | L40: C | M40: C | N40: C | O40: C | Q40: C
A41: Business Understanding | B41: Change impact assessment | C41: I | D41: C | E41: A | F41: S | G41: C | J41: C | O41: C | P41: C | Q41: R
A42: Business Understanding | B42: Stakeholder analysis and engagement map | C42: I | D42: C | E42: A | F42: S | G42: C | J42: C | P42: C | Q42: R
A43: Business Understanding | B43: Change strategy and case for change | C43: A | D43: C | E43: R | F43: S | G43: C | J43: C | P43: C | Q43: R
A44: Data Understanding | B44: Communication plan and launch narrative | C44: I | D44: C | E44: A | F44: S | G44: C | J44: C | P44: C | Q44: R
A45: Data Understanding | B45: Training needs analysis | C45: I | D45: I | E45: A | F45: S | G45: C | J45: C | P45: C | Q45: R
A46: Data Understanding | B46: Adoption readiness baseline survey | C46: I | D46: I | E46: A | F46: S | G46: C | J46: C | P46: C | Q46: R
A47: Modeling | B47: Develop training and enablement assets | C47: I | D47: I | E47: A | F47: S | G47: C | J47: C | N47: C | P47: C | Q47: R
A48: Modeling | B48: Champion network setup | C48: I | D48: I | E48: A | F48: S | G48: C | J48: C | P48: C | Q48: R
A49: Modeling | B49: Change readiness check and resistance plan | C49: A | D49: C | E49: C | F49: S | G49: C | J49: C | P49: C | Q49: R
A50: Evaluation | B50: Finalise launch comms and onboarding pack | C50: I | D50: C | E50: A | F50: S | G50: C | J50: C | P50: C | Q50: R
A51: Evaluation | B51: Adoption measurement plan and post-launch cadence | C51: I | D51: C | E51: A | F51: S | G51: C | J51: C | P51: C | Q51: R
A52: Delivery | B52: Sprint planning and capacity management | C52: I | D52: I | E52: A | F52: C | G52: C | H52: C | I52: C | J52: C | K52: C | L52: C | M52: C | N52: C | Q52: C | R52: R
A53: Delivery | B53: Sprint review, demo and retrospective | C53: I | D53: C | E53: A | F53: S | G53: C | H53: C | I53: C | J53: C | K53: C | L53: C | M53: C | N53: C | Q53: C | R53: R
A54: Delivery | B54: Sprint performance tracking and velocity forecast | C54: I | D54: C | E54: A | F54: C | R54: R
A55: Business Understanding | B55: Define CV structure and work profile fields | C55: I | D55: I | E55: A | F55: S | G55: C | H55: C | I55: C | M55: C | P55: C | Q55: C
A56: Data Understanding | B56: Agree CV review cadence and update policy | C56: A | D56: C | E56: R | F56: S | G56: C | J56: C | M56: C | O56: C | Q56: C
A57: Modeling | B57: Design CV builder and work profile screens | C57: I | D57: I | E57: A | F57: S | G57: R | H57: C | I57: C | J57: C | N57: C | P57: C
A58: Evaluation | B58: Validate CV builder and profile update flow | C58: I | D58: I | E58: A | F58: S | G58: R | H58: C | J58: C | N58: C | Q58: C
A59: Business Understanding | B59: Confirm Slack and WhatsApp channel scope | C59: A | D59: C | E59: R | F59: S | G59: C | I59: C | L59: C | M59: C | O59: C | Q59: C | R59: R
A60: Data Understanding | B60: Channel identity model and opt-in policy | C60: A | D60: C | E60: C | F60: S | I60: C | L60: C | M60: C | O60: R | Q60: C | R60: R
A61: Modeling | B61: Spec inbound and outbound channel handling | C61: I | D61: C | E61: C | F61: S | I61: C | K61: C | L61: C | M61: R | N61: C | O61: C | R61: A
A62: Evaluation | B62: Channel end-to-end and security test | C62: I | D62: C | E62: A | F62: S | I62: C | K62: C | L62: C | M62: C | N62: C | O62: C | R62: R
A63: S0 | B63: Toolchain, spikes and migrations - close G0 | C63: R | D63: A | E63: C
A64: S1-S2 | B64: Database baseline, W0 auth and admin - G1 and G-RB | C64: R | D64: A | E64: C | F64: I
A65: S3-S7 | B65: Build packs W0-W5 including gated options - G-AI, G-CH, G-CF | C65: R | D65: A | E65: I
A66: S8-S11 | B66: Build packs W5-W7 and the descope lane - G2 and G3 | C66: R | D66: A | E66: C
A67: S12-S13 | B67: Hardening, UAT and go-live - G4, G5 and gate 8.0 | C67: R | D67: A | E67: C | F67: I
A68: S14-S15 | B68: Pilot with ~50 members, hypercare and handover | C68: R | D68: A | E68: I

Sheet RAID Log
A1: RAID Log - Risks, Assumptions, Issues, Dependencies
A2: Living register aligned to the delivery board: G0 blockers, gated build options and the descope lane. Reviewed weekly at the PMO stand-up; high items escalate to the Steering Committee.
A4: Register
A5: ID | B5: Type | C5: Description | D5: Category | E5: Probability / Impact | F5: Score | G5: Owner | H5: Mitigation / Response | I5: Due Date | J5: Status
A6: R-001 | B6: Risk | C6: Oracle Sans web licence for the alumni domain is not secured in time | D6: Brand | E6: Medium / High | F6: 12 | G6: Brand Review Lead | H6: Confirm licence or proceed on the Albert Sans fallback; decide at Gate 2. | I6: [date] | J6: Open
A7: R-002 | B7: Risk | C7: Leadership letter author and portrait approval delays the Home hero | D7: Content | E7: Medium / High | F7: 12 | G7: Content Strategist | H7: Start approval early; use a placeholder slide until sign-off. | I7: [date] | J7: Open
A8: R-003 | B8: Risk | C8: Alumni profile data is incomplete or contains raw null / N-A values | D8: Data | E8: High / Medium | F8: 12 | G8: Data / Privacy Officer | H8: Data quality assessment; enforce graceful fallbacks ('-', 'Open to opportunities'). | I8: [date] | J8: Open
A9: R-004 | B9: Risk | C9: Directory-visibility default (opt-in vs opt-out) is unresolved and blocks the directory | D9: Privacy | E9: Medium / High | F9: 12 | G9: Privacy Officer | H9: Decide at the Privacy & Compliance Board in week 2; document the consent model. | I9: [date] | J9: Open
A10: R-005 | B10: Risk | C10: Scope creep beyond v1 (admin / CMS console, native apps, analytics dashboards) | D10: Scope | E10: High / Medium | F10: 12 | G10: Product Owner | H10: Baselined out-of-scope list; change control via Steering Committee. | I10: [date] | J10: Open
A11: R-006 | B11: Risk | C11: Accessibility (WCAG 2.2 AA) gaps found late in the build | D11: Compliance | E11: Medium / High | F11: 12 | G11: Accessibility Lead | H11: Accessibility spec in week 2; prototype review in week 3; audit in week 4. | I11: [date] | J11: Open
A12: R-007 | B12: Risk | C12: Low alumni adoption after launch | D12: Adoption | E12: Medium / High | F12: 12 | G12: Change & Comms Lead | H12: Launch comms, content cadence, champions, profile nudges; track return visits weekly. | I12: [date] | J12: Open
A13: R-008 | B13: Risk | C13: Reference-portal patterns leak through instead of Oracle brand | D13: Brand | E13: Medium / Medium | F13: 9 | G13: Brand Review Lead | H13: Design Authority review at each gate; brand substitution table applied globally. | I13: [date] | J13: Open
A14: R-009 | B14: Risk | C14: Integration with Oracle Careers / events / HR is harder than expected | D14: Technical | E14: Medium / Medium | F14: 9 | G14: Solution Architect | H14: Confirm integration map in week 2; define deep-link fallbacks. | I14: [date] | J14: Open
A15: A-001 | B15: Assumption | C15: Alumni data and directory fields are available for the build | D15: Data | E15: Medium / High | F15: 12 | G15: Data / Privacy Officer | H15: Confirm availability in Data Understanding; escalate gaps. | I15: [date] | J15: Open
A16: A-002 | B16: Assumption | C16: SSO / verified-email authentication is available for the alumni domain | D16: Technical | E16: Medium / High | F16: 12 | G16: Solution Architect | H16: Confirm auth approach in week 2. | I16: [date] | J16: Open
... A49: D-014 | B49: Dependency | C49: Temporary 100k load-test ADB to be booked for the full load test (G2) | D49: Infrastructure | E49: Medium / High | F49: M | G49: Solution Architect | H49: Book before S8; used for the full load test in S9 | I49: S8 (G2) | J49: Open
A51: Scoring and status key
A52: Probability | C52: High = >60% likely | Medium = 20-60% | Low = <20%
A53: Impact | C53: High = major (cost, schedule, brand, compliance) | Medium = moderate | Low = minor
A54: Score | C54: Probability x Impact (High=3, Medium=2, Low=1); 6-9 = high priority, 3-5 = medium, 1-2 = low
A55: Status | C55: Open | In Progress | Mitigated | Closed | Escalated
A56: Review | C56: Reviewed weekly at PMO stand-up; high items reported to Steering Committee.

Sheet Artefact Register
A1: Artefact Register - Plan Aligned to Deliverables
A2: Every programme artefact, its version, its owner and the plan workstream that produces it. This is how the plan stays aligned with the artefacts.
A4: Artefact ID | B4: Artefact | C4: Type | D4: Version | E4: Owner | F4: Plan Workstream | G4: Governing FRs | H4: Status
A5: A-01 | B5: Functional Specification (FSD) | C5: Document | D5: 1.1 | E5: Product Owner | F5: Business Understanding | G5: FR-01 to FR-24 | H5: Draft for review
A6: A-02 | B6: Database schema (Oracle DDL) | C6: SQL | D6: 1.1 | E6: AI Architect | F6: Data Understanding | G6: Data model for all FRs | H6: Ready for build
A7: A-03 | B7: Data dictionary | C7: Spreadsheet | D7: 1.1 | E7: Data Steward | F7: Data Understanding | G7: Data model for all FRs | H7: Ready for build
A8: A-04 | B8: Entity relationship diagram | C8: Diagram | D8: 1.1 | E8: AI Architect | F8: Data Understanding | G8: Data model for all FRs | H8: Ready for build
A9: A-05 | B9: OAN_CHAT_API package | C9: PL/SQL | D9: 1.1 | E9: Integration / Channel Lead | F9: Modeling | G9: FR-01, FR-17, FR-23, FR-24 | H9: Skeleton delivered
A10: A-06 | B10: OAN_NOTIFY_API package | C10: PL/SQL | D10: 1.1 | E10: Integration / Channel Lead | F10: Modeling | G10: FR-16, FR-23, FR-24 | H10: Skeleton delivered
A11: A-07 | B11: APEX Application Build Pack | C11: Document | D11: 1.1 | E11: Scrum Master / Delivery Lead | F11: Modeling | G11: All FRs (build order) | H11: Draft for review
A12: A-08 | B12: APEX Build Tracker | C12: Spreadsheet | D12: 1.1 | E12: Scrum Master / Delivery Lead | F12: Delivery | G12: All FRs (page inventory) | H12: In use
A13: A-09 | B13: CXO Build Plan and Build Order deck | C13: Presentation | D13: 1.0 | E13: Product Owner | F13: Governance | G13: All FRs (executive view) | H13: For steering review
A14: A-10 | B14: Project Plan (CPMAI) | C14: Spreadsheet | D14: 1.1 | E14: Project Manager | F14: Governance | G14: All FRs (delivery) | H14: Draft for review
A15: A-11 | B15: Sprint Capacity Planner | C15: Spreadsheet | D15: 1.0 | E15: Scrum Master / Delivery Lead | F15: Delivery | G15: Delivery capacity | H15: In use
... A24: A-20 | B24: Sprint Roadmap (16 sprints S0-S15 and 11 gates) | C24: Plan | D24: V3.2 | E24: Scrum Master / Delivery Lead | F24: Capacity management | G24: All 24 FRs | H24: Live
A26: Alignment rules
A27: - A change to any artefact updates its version here and re-runs the affected workstream tasks.
A28: - The Functional Specification governs every other artefact; the schema, packages and build pack must trace to it.
A29: - The build pack and build tracker are regenerated whenever a page, grid or API routine changes.
A30: - The CXO deck is refreshed from the build pack before every steering review.
A31: - The project plan, RAID log and capacity planner are updated weekly and at every gate.

Sheet Sprint Capacity Planner
A1: Sprint Capacity Planner - Oracle Alumni Network Portal
A2: Plans one sprint at a time. Pale-yellow cells are editable inputs; white cells calculate automatically.
A4: Activity | B4: Product Owner | C4: Scrum Master / Delivery Lead | D4: UX Lead | E4: UI / Visual Designer | F4: Design Systems / Front-end | G4: Back-end Engineer | H4: Solution Architect | I4: Accessibility / QA Lead | J4: Content Strategist | K4: Change & Comms Lead | L4: Total | N4: SPRINT & ASSUMPTIONS
A5: Sprint Planning | B5: =$O$9 -> 4 | C5: =$O$9 -> 4 | D5: =$O$9 -> 4 | E5: =$O$9 -> 4 | F5: =$O$9 -> 4 | G5: =$O$9 -> 4 | H5: =$O$9 -> 4 | I5: =$O$9 -> 4 | ... K5: =$O$9 -> 4 | L5: =SUM(B5:K5) -> 40 | N5: Sprint Number | O5: S1 (Build)
A6: Backlog Grooming / Tasking | B6: =$O$10 -> 4 | C6: =$O$10 -> 4 | D6: =$O$10 -> 4 | E6: =$O$10 -> 4 | F6: =$O$10 -> 4 | G6: =$O$10 -> 4 | H6: =$O$10 -> 4 | I6: =$O$10 -> 4 | ... K6: =$O$10 -> 4 | L6: =SUM(B6:K6) -> 40 | N6: Sprint Start Date | O6: 46328
A7: Daily Stand-up | B7: =$O$11/60*$O$19 -> 2.5 | C7: =$O$11/60*$O$19 -> 2.5 | D7: =$O$11/60*$O$19 -> 2.5 | E7: =$O$11/60*$O$19 -> 2.5 | F7: =$O$11/60*$O$19 -> 2.5 | G7: =$O$11/60*$O$19 -> 2.5 | H7: =$O$11/60*$O$19 -> 2.5 | I7: =$O$11/60*$O$19 -> 2.5 | ... K7: =$O$11/60*$O$19 -> 2.5 | L7: =SUM(B7:K7) -> 25 | N7: Sprint End Date | O7: 46339
A8: Sprint Retrospective | B8: =$O$12 -> 1.5 | C8: =$O$12 -> 1.5 | D8: =$O$12 -> 1.5 | E8: =$O$12 -> 1.5 | F8: =$O$12 -> 1.5 | G8: =$O$12 -> 1.5 | H8: =$O$12 -> 1.5 | I8: =$O$12 -> 1.5 | ... K8: =$O$12 -> 1.5 | L8: =SUM(B8:K8) -> 15 | N8: Hours per Working Day | O8: 8
A9: Sprint Review | B9: =$O$13 -> 1.5 | C9: =$O$13 -> 1.5 | D9: =$O$13 -> 1.5 | E9: =$O$13 -> 1.5 | F9: =$O$13 -> 1.5 | G9: =$O$13 -> 1.5 | H9: =$O$13 -> 1.5 | I9: =$O$13 -> 1.5 | ... K9: =$O$13 -> 1.5 | L9: =SUM(B9:K9) -> 15 | N9: Sprint Planning (hrs/person) | O9: 4
A10: Sprint Demo | B10: =$O$14 -> 1 | C10: =$O$14 -> 1 | D10: =$O$14 -> 1 | E10: =$O$14 -> 1 | F10: =$O$14 -> 1 | G10: =$O$14 -> 1 | H10: =$O$14 -> 1 | I10: =$O$14 -> 1 | ... K10: =$O$14 -> 1 | L10: =SUM(B10:K10) -> 10 | N10: Backlog Grooming (hrs/person) | O10: 4
A11: Sub-total: Repeating Ceremonies | B11: =SUM(B5:B10) -> 14.5 | C11: =SUM(C5:C10) -> 14.5 | D11: =SUM(D5:D10) -> 14.5 | E11: =SUM(E5:E10) -> 14.5 | F11: =SUM(F5:F10) -> 14.5 | G11: =SUM(G5:G10) -> 14.5 | H11: =SUM(H5:H10) -> 14.5 | I11: =SUM(I5:I10) -> 14.5 | ... K11: =SUM(K5:K10) -> 14.5 | L11: =SUM(B11:K11) -> 145 | N11: Daily Standup (min/day) | O11: 15
A12: Adhoc Meetings | B12: =$O$15 -> 2.5 | C12: =$O$15 -> 2.5 | D12: =$O$15 -> 2.5 | E12: =$O$15 -> 2.5 | F12: =$O$15 -> 2.5 | G12: =$O$15 -> 2.5 | H12: =$O$15 -> 2.5 | I12: =$O$15 -> 2.5 | ... K12: =$O$15 -> 2.5 | L12: =SUM(B12:K12) -> 25 | N12: Sprint Retrospective (hrs) | O12: 1.5
A13: Sub-total: Non-Scrum Meetings | B13: =B12 -> 2.5 | C13: =C12 -> 2.5 | D13: =D12 -> 2.5 | E13: =E12 -> 2.5 | F13: =F12 -> 2.5 | G13: =G12 -> 2.5 | H13: =H12 -> 2.5 | I13: =I12 -> 2.5 | ... K13: =K12 -> 2.5 | L13: =SUM(B13:K13) -> 25 | N13: Sprint Review (hrs) | O13: 1.5
A14: Total Meeting Load | B14: =B11+B13 -> 17 | C14: =C11+C13 -> 17 | D14: =D11+D13 -> 17 | E14: =E11+E13 -> 17 | F14: =F11+F13 -> 17 | G14: =G11+G13 -> 17 | H14: =H11+H13 -> 17 | I14: =I11+I13 -> 17 | ... K14: =K11+K13 -> 17 | L14: =SUM(B14:K14) -> 170 | N14: Sprint Demo (hrs) | O14: 1
A15: Resource Allocation % | B15: 0.5 | C15: 0.5 | D15: 1 | E15: 1 | F15: 1 | G15: 1 | H15: 0.5 | I15: 1 | J15: 0.5 | K15: 0.5 | L15: Team | N15: Adhoc Meetings buffer (hrs/person) | O15: 2.5
A16: Total Available Time | B16: =$O$20*B15 -> 40 | C16: =$O$20*C15 -> 40 | D16: =$O$20*D15 -> 80 | E16: =$O$20*E15 -> 80 | F16: =$O$20*F15 -> 80 | G16: =$O$20*G15 -> 80 | H16: =$O$20*H15 -> 40 | I16: =$O$20*I15 -> 80 | ... K16: =$O$20*K15 -> 40 | L16: =SUM(B16:K16) -> 600 | N16: Holidays in this Sprint (days) | O16: 0
A17: Vacation / Leave (hrs) | B17: 0 | C17: 0 | D17: 0 | E17: 0 | F17: 0 | G17: 0 | H17: 0 | I17: 0 | J17: 0 | K17: 0 | L17: =SUM(B17:K17) -> 0 | N17: Avg Hours per Story Point | O17: 8
A18: Public Holiday (hrs) | B18: 0 | C18: 0 | D18: 0 | E18: 0 | F18: 0 | G18: 0 | H18: 0 | I18: 0 | J18: 0 | K18: 0 | L18: =SUM(B18:K18) -> 0 | N18: Planning Risk Buffer % | O18: 0.1
A19: Actual Available Hours | B19: =B16-B14-B17-B18 -> 23 | C19: =C16-C14-C17-C18 -> 23 | D19: =D16-D14-D17-D18 -> 63 | E19: =E16-E14-E17-E18 -> 63 | F19: =F16-F14-F17-F18 -> 63 | G19: =G16-G14-G17-G18 -> 63 | H19: =H16-H14-H17-H18 -> 23 | I19: =I16-I14-I17-I18 -> 63 | ... K19: =K16-K14-K17-K18 -> 23 | L19: =SUM(B19:K19) -> 430 | N19: Sprint Working Days (auto) | O19: =NETWORKDAYS(O6,O7)-O16 -> 10
A20: Maturity / Ramp-up Level | B20: 1 | C20: 1 | D20: 1 | E20: 1 | F20: 1 | G20: 1 | H20: 1 | I20: 1 | J20: 1 | K20: 1 | L20: Factor | N20: Total Sprint Hours per FTE (auto) | O20: =O19*O8 -> 80
A21: Hours Available for Sprint | B21: =MAX(0,B19*B20) -> 23 | C21: =MAX(0,C19*C20) -> 23 | D21: =MAX(0,D19*D20) -> 63 | E21: =MAX(0,E19*E20) -> 63 | F21: =MAX(0,F19*F20) -> 63 | G21: =MAX(0,G19*G20) -> 63 | H21: =MAX(0,H19*H20) -> 23 | I21: =MAX(0,I19*I20) -> 63 | ... K21: =MAX(0,K19*K20) -> 23 | L21: =SUM(B21:K21) -> 430
A22: Story-Point Capacity | B22: =B21/$O$17 -> 2.875 | C22: =C21/$O$17 -> 2.875 | D22: =D21/$O$17 -> 7.875 | E22: =E21/$O$17 -> 7.875 | F22: =F21/$O$17 -> 7.875 | G22: =G21/$O$17 -> 7.875 | H22: =H21/$O$17 -> 2.875 | I22: =I21/$O$17 -> 7.875 | ... K22: =K21/$O$17 -> 2.875 | L22: =SUM(B22:K22) -> 53.75
A24: Expected Team Velocity (SP) | B24: =L22 -> 53.75
A25: Risk-Adjusted Velocity (after buffer) | B25: =B24*(1-$O$18) -> 48.375
A26: Spill-Over Points from Previous Sprint | B26: 0
A27: Recommended Sprint Commitment (SP) | B27: =B25-B26 -> 48.375
A28: Final Committed SP (team decision) | B28: 0
A30: Legend
A31: Pale yellow = editable input | White = calculated by formula
A32: Sprint Working Days is calculated with NETWORKDAYS from the sprint start and end dates, less holidays.
A33: Story-Point Capacity = Hours Available for Sprint / Avg Hours per Story Point.
A34: Recommended Sprint Commitment = Risk-Adjusted Velocity - Spill-Over Points. The team agrees the final number.

Sheet Sprint Performance Tracker
A1: Sprint Performance Tracker - Oracle Alumni Network Portal
A2: Logs every closed sprint. Completion, utilisation, 3-sprint trend and next-sprint forecast are calculated.
A3: Rows below are an ILLUSTRATIVE BASELINE carried from the attached planner - replace with your actual sprint data.
A5: Sprint | B5: Start Date | C5: End Date | D5: Holidays (days) | E5: Working Days | F5: Team Capacity (SP) | G5: Committed (SP) | H5: Delivered (SP) | I5: Completion % | J5: Capacity Utilisation % | K5: 3-Sprint Avg Delivered | L5: Trend | M5: Sprint Index
A6: Sprint 1 | B6: 46111 | C6: 46122 | D6: 0 | E6: =NETWORKDAYS(B6,C6)-D6 -> 10 | F6: 34 | G6: 32 | H6: 27 | I6: =IF(G6=0,0,H6/G6) -> 0.84375 | J6: =IF(F6=0,0,H6/F6) -> 0.79411765 | K6: =AVERAGE(H6:H6) -> 27 | L6: — | M6: 1
A7: Sprint 2 | B7: 46125 | C7: 46136 | D7: 0 | E7: =NETWORKDAYS(B7,C7)-D7 -> 10 | F7: 36 | G7: 34 | H7: 30 | I7: =IF(G7=0,0,H7/G7) -> 0.88235294 | J7: =IF(F7=0,0,H7/F7) -> 0.83333333 | K7: =AVERAGE(H6:H7) -> 28.5 | L7: =IF(K7>K6,"▲ Improving",IF(K7<K6,"▼ Declining","▬ Stable")) -> ▲ Improving | M7: 2
A8: Sprint 3 | B8: 46139 | C8: 46150 | D8: 0 | E8: =NETWORKDAYS(B8,C8)-D8 -> 10 | F8: 33 | G8: 30 | H8: 25 | I8: =IF(G8=0,0,H8/G8) -> 0.83333333 | J8: =IF(F8=0,0,H8/F8) -> 0.75757576 | K8: =AVERAGE(H6:H8) -> 27.333333 | L8: =IF(K8>K7,"▲ Improving",IF(K8<K7,"▼ Declining","▬ Stable")) -> ▼ Declining | M8: 3
A9: Sprint 4 | B9: 46153 | C9: 46164 | D9: 1 | E9: =NETWORKDAYS(B9,C9)-D9 -> 9 | F9: 38 | G9: 36 | H9: 33 | I9: =IF(G9=0,0,H9/G9) -> 0.91666667 | J9: =IF(F9=0,0,H9/F9) -> 0.86842105 | K9: =AVERAGE(H7:H9) -> 29.333333 | L9: =IF(K9>K8,"▲ Improving",IF(K9<K8,"▼ Declining","▬ Stable")) -> ▲ Improving | M9: 4
A10: Sprint 5 | B10: 46167 | C10: 46178 | D10: 0 | E10: =NETWORKDAYS(B10,C10)-D10 -> 10 | F10: 35 | G10: 33 | H10: 29 | I10: =IF(G10=0,0,H10/G10) -> 0.87878788 | J10: =IF(F10=0,0,H10/F10) -> 0.82857143 | K10: =AVERAGE(H8:H10) -> 29 | L10: =IF(K10>K9,"▲ Improving",IF(K10<K9,"▼ Declining","▬ Stable")) -> ▼ Declining | M10: 5
A11: Sprint 6 | B11: 46181 | C11: 46192 | D11: 0 | E11: =NETWORKDAYS(B11,C11)-D11 -> 10 | F11: 40 | G11: 38 | H11: 35 | I11: =IF(G11=0,0,H11/G11) -> 0.92105263 | J11: =IF(F11=0,0,H11/F11) -> 0.875 | K11: =AVERAGE(H9:H11) -> 32.333333 | L11: =IF(K11>K10,"▲ Improving",IF(K11<K10,"▼ Declining","▬ Stable")) -> ▲ Improving | M11: 6
A12: Sprint 7 | B12: 46195 | C12: 46206 | D12: 0 | E12: =NETWORKDAYS(B12,C12)-D12 -> 10 | F12: 37 | G12: 35 | H12: 33 | I12: =IF(G12=0,0,H12/G12) -> 0.94285714 | J12: =IF(F12=0,0,H12/F12) -> 0.89189189 | K12: =AVERAGE(H10:H12) -> 32.333333 | L12: =IF(K12>K11,"▲ Improving",IF(K12<K11,"▼ Declining","▬ Stable")) -> ▬ Stable | M12: 7
A13: Sprint 8 | B13: 46209 | C13: 46220 | D13: 0 | E13: =NETWORKDAYS(B13,C13)-D13 -> 10 | F13: 42 | G13: 40 | H13: 37 | I13: =IF(G13=0,0,H13/G13) -> 0.925 | J13: =IF(F13=0,0,H13/F13) -> 0.88095238 | K13: =AVERAGE(H11:H13) -> 35 | L13: =IF(K13>K12,"▲ Improving",IF(K13<K12,"▼ Declining","▬ Stable")) -> ▲ Improving | M13: 8
A14: Sprint 9 | B14: 46223 | C14: 46234 | D14: 1 | E14: =NETWORKDAYS(B14,C14)-D14 -> 9 | F14: 39 | G14: 37 | H14: 35 | I14: =IF(G14=0,0,H14/G14) -> 0.94594595 | J14: =IF(F14=0,0,H14/F14) -> 0.8974359 | K14: =AVERAGE(H12:H14) -> 35 | L14: =IF(K14>K13,"▲ Improving",IF(K14<K13,"▼ Declining","▬ Stable")) -> ▬ Stable | M14: 9
A15: Sprint 10 | B15: 46237 | C15: 46248 | D15: 0 | E15: =NETWORKDAYS(B15,C15)-D15 -> 10 | F15: 44 | G15: 42 | H15: 39 | I15: =IF(G15=0,0,H15/G15) -> 0.92857143 | J15: =IF(F15=0,0,H15/F15) -> 0.88636364 | K15: =AVERAGE(H13:H15) -> 37 | L15: =IF(K15>K14,"▲ Improving",IF(K15<K14,"▼ Declining","▬ Stable")) -> ▲ Improving | M15: 10
A16: Sprint 11 | B16: 46251 | C16: 46262 | D16: 0 | E16: =NETWORKDAYS(B16,C16)-D16 -> 10 | F16: 41 | G16: 39 | H16: 37 | I16: =IF(G16=0,0,H16/G16) -> 0.94871795 | J16: =IF(F16=0,0,H16/F16) -> 0.90243902 | K16: =AVERAGE(H14:H16) -> 37 | L16: =IF(K16>K15,"▲ Improving",IF(K16<K15,"▼ Declining","▬ Stable")) -> ▬ Stable | M16: 11
A17: Sprint 12 | B17: 46265 | C17: 46276 | D17: 0 | E17: =NETWORKDAYS(B17,C17)-D17 -> 10 | F17: 46 | G17: 44 | H17: 42 | I17: =IF(G17=0,0,H17/G17) -> 0.95454545 | J17: =IF(F17=0,0,H17/F17) -> 0.91304348 | K17: =AVERAGE(H15:H17) -> 39.333333 | L17: =IF(K17>K16,"▲ Improving",IF(K17<K16,"▼ Declining","▬ Stable")) -> ▲ Improving | M17: 12
A19: Trend & forecast
A20: Velocity trend (SP gained per sprint) | D20: =SLOPE(H6:H17,M6:M17) -> 1.2517483
A21: Next sprint forecast — delivered SP | D21: =FORECAST(13,H6:H17,M6:M17) -> 41.636364
A22: Average completion rate (all sprints) | D22: =AVERAGE(I6:I17) -> 0.91013178
A23: Average capacity utilisation (all sprints) | D23: =AVERAGE(J6:J17) -> 0.86076213
A25: Live dashboard
A26: Current sprint capacity (SP) | D26: ='Sprint Capacity Planner'!B24 -> 53.75
A27: Risk-adjusted capacity (SP) | D27: ='Sprint Capacity Planner'!B25 -> 48.375
A28: Recommended commitment (SP) | D28: ='Sprint Capacity Planner'!B27 -> 48.375
A29: Average completion rate | D29: =D23 -> 0.86076213
A30: Next sprint forecast (SP) | D30: =D22 -> 0.91013178
A32: Resource hours — current sprint (from the Capacity Planner)
A33: Resource | B33: Role | C33: Hours Available | D33: Story-Point Capacity | E33: Allocation % | F33: Maturity
A34: Resource 1 | B34: Product Owner | C34: ='Sprint Capacity Planner'!B19 -> 23 | D34: ='Sprint Capacity Planner'!B22 -> 2.875 | E34: ='Sprint Capacity Planner'!B15 -> 0.5 | F34: ='Sprint Capacity Planner'!B20 -> 1
A35: Resource 2 | B35: Scrum Master / Delivery Lead | C35: ='Sprint Capacity Planner'!C19 -> 23 | D35: ='Sprint Capacity Planner'!C22 -> 2.875 | E35: ='Sprint Capacity Planner'!C15 -> 0.5 | F35: ='Sprint Capacity Planner'!C20 -> 1
A36: Resource 3 | B36: UX Lead | C36: ='Sprint Capacity Planner'!D19 -> 63 | D36: ='Sprint Capacity Planner'!D22 -> 7.875 | E36: ='Sprint Capacity Planner'!D15 -> 1 | F36: ='Sprint Capacity Planner'!D20 -> 1
A37: Resource 4 | B37: UI / Visual Designer | C37: ='Sprint Capacity Planner'!E19 -> 63 | D37: ='Sprint Capacity Planner'!E22 -> 7.875 | E37: ='Sprint Capacity Planner'!E15 -> 1 | F37: ='Sprint Capacity Planner'!E20 -> 1
A38: Resource 5 | B38: Design Systems / Front-end | C38: ='Sprint Capacity Planner'!F19 -> 63 | D38: ='Sprint Capacity Planner'!F22 -> 7.875 | E38: ='Sprint Capacity Planner'!F15 -> 1 | F38: ='Sprint Capacity Planner'!F20 -> 1
A39: Resource 6 | B39: Back-end Engineer | C39: ='Sprint Capacity Planner'!G19 -> 63 | D39: ='Sprint Capacity Planner'!G22 -> 7.875 | E39: ='Sprint Capacity Planner'!G15 -> 1 | F39: ='Sprint Capacity Planner'!G20 -> 1
A40: Resource 7 | B40: Solution Architect | C40: ='Sprint Capacity Planner'!H19 -> 23 | D40: ='Sprint Capacity Planner'!H22 -> 2.875 | E40: ='Sprint Capacity Planner'!H15 -> 0.5 | F40: ='Sprint Capacity Planner'!H20 -> 1
A41: Resource 8 | B41: Accessibility / QA Lead | C41: ='Sprint Capacity Planner'!I19 -> 63 | D41: ='Sprint Capacity Planner'!I22 -> 7.875 | E41: ='Sprint Capacity Planner'!I15 -> 1 | F41: ='Sprint Capacity Planner'!I20 -> 1
A42: Resource 9 | B42: Content Strategist | C42: ='Sprint Capacity Planner'!J19 -> 23 | D42: ='Sprint Capacity Planner'!J22 -> 2.875 | E42: ='Sprint Capacity Planner'!J15 -> 0.5 | F42: ='Sprint Capacity Planner'!J20 -> 1
A43: Resource 10 | B43: Change & Comms Lead | C43: ='Sprint Capacity Planner'!K19 -> 23 | D43: ='Sprint Capacity Planner'!K22 -> 2.875 | E43: ='Sprint Capacity Planner'!K15 -> 0.5 | F43: ='Sprint Capacity Planner'!K20 -> 1

Sheet Sprint Roadmap
A1: Sprint Roadmap - 16 Sprints S0-S15 and the 11 Gates
A2: Sprint sequence from the attached delivery board (Plan V3.2, iteration 9). Capacity per sprint is planned on the Sprint Capacity Planner.
A4: Sprint | B4: Sprint Window | C4: CPMAI Phase | D4: Focus / Screens | E4: Key Deliverable | F4: Exit / Gate
A5: S0 | B5: 19-30 Oct 2026 | C5: Phase 1-4 (setup) | D5: Toolchain, spikes, migrations; design system and 8 core screens continue in parallel | E5: Toolchain ready, migrations validated | F5: G0
A6: S1 | B6: 2-13 Nov 2026 | C6: Phase 5 (Deployment) | D6: First shared DB deploy - DDL, security, auth packages | E6: db-baseline-v1 deployed
A7: S2 | B7: 16-27 Nov 2026 | C7: Phase 5 (Deployment) | D7: DB tests, W0 auth + admin pages | E7: W0 pages and DB tests green | F7: G1, G-RB
A8: S3 | B8: 30 Nov-11 Dec 2026 | C8: Phase 5 (Deployment) | D8: W0 onboarding, W1 shell | E8: Onboarding and shell live in DEV | F8: G-AI
A9: S4 | B9: 14-25 Dec 2026 | C9: Phase 5 (Deployment) | D9: W2 profile + directory tables and index | E9: Profile and directory foundation
A10: S5 | B10: 28 Dec 2026-8 Jan 2027 | C10: Phase 5 (Deployment) | D10: W2 CV and privacy; product-owner demo 1 | E10: My CV + current work profile (pages 24, 25)
A11: S6 | B11: 11-22 Jan 2027 | C11: Phase 5 (Deployment) | D11: W3 content, W4 messaging package | E11: Content and messaging live | F11: G-CH
A12: S7 | B12: 25 Jan-5 Feb 2027 | C12: Phase 5 (Deployment) | D12: W4 channels, W5 organisations | E12: Slack + WhatsApp channels (page 43) | F12: G-CF
A13: S8 | B13: 8-19 Feb 2027 | C13: Phase 5 (Deployment) | D13: W5 jobs, helpdesk, W6 experts; demo 2 | E13: Jobs, helpdesk and expert network | F13: G2
A14: S9 | B14: 22 Feb-5 Mar 2027 | C14: Phase 5 (Deployment) | D14: W6 groups, partner workspace, mentoring | E14: Community and partner surface
A15: S10 | B15: 8-19 Mar 2027 | C15: Phase 5 (Deployment) | D15: W6 training, initiatives; demo 3; buffer | E15: Training and initiatives | F15: G3
A16: S11 | B16: 22 Mar-2 Apr 2027 | C16: Phase 5 (Deployment) | D16: W7 reports; descope lane active | E16: Admin dashboard and analytics
A17: S12 | B17: 5-16 Apr 2027 | C17: Phase 5 (Hardening) | D17: Load, WCAG 2.2 AA, security, full UAT | E17: Full AC regression and UAT sign-off | F17: G4, G5
A18: S13 | B18: 19-30 Apr 2027 | C18: Phase 5 (Release) | D18: Gate 8.0 and PROD release | E18: Production go-live | F18: 8.0
A19: S14 | B19: 3-14 May 2027 | C19: Phase 6 (Monitoring) | D19: Pilot ~50 members, every staff role, >= 3 orgs | E19: Pilot validated
A20: S15 | B20: 17-28 May 2027 | C20: Phase 6 (Monitoring) | D20: Hypercare (2 weeks) and handover | E20: Handover + v1.x backlog
A22: S0 is the setup sprint, with the design system and 8 core screens proceeding in parallel. Build sprints are 2 weeks, planned with velocity-based capacity and a planning-risk buffer. S11 carries the descope lane; S12-S15 cover hardening, go-live, pilot and hypercare.

Sheet Board Tasks
A1: Board Tasks - the 154 tracked cards behind the Kanban
A2: One row per card on the attached delivery board. The Kanban Board and Kanban Dashboard read this sheet.
A4: ID | B4: Task | C4: Category | D4: Dev pd | E4: Priority | F4: Status
A5: 0.16a | B5: Liquibase changelog (forward-only) | C5: Environment | D5: 1.5 | E5: P0 | F5: Not started
A6: 0.16c | B6: Scratch-schema rebuild each sprint | C6: Environment | D6: 0.5 | E6: P0 | F6: Not started
A7: 0.18 | B7: Spike: APEX GenAI service | C7: Environment | D7: 0.5 | E7: P4 | F7: Not started
A8: 0.19 | B8: Procure Slack app, WhatsApp Business | C8: Environment | D8: OAN | E8: P4 | F8: Not started
A9: 0.1b | B9: Local Oracle DB Free + utPLSQL (optional) | C9: Environment | D9: 1 | E9: P4 | F9: Not started
A10: 0.20 | B10: ORDS install: OAN_API schema, channel modules | C10: Environment | D10: 1 | E10: P4 | F10: Not started
A11: 0.7 | B11: OCI Email Delivery + APEX SMTP | C11: Environment | D11: 0.5 | E11: P0 | F11: Not started
A12: 1.29 | B12: Traceability + Must/Should/Could AC tags | C12: Database | D12: 1.5 | E12: P0 | F12: Not started
A13: 5.1 | B13: Full AC regression + evidence pack | C13: Quality | D13: 4 | E13: P0 | F13: Not started
A14: 5.10 | B14: J-01..J-21 end-to-end regression | C14: Quality | D14: 3 | E14: P0 | F14: Not started
A15: 5.2 | B15: Security test (ZAP, bypass, leaks) | C15: Quality | D15: 3 | E15: P0 | F15: Not started
A16: 5.3a | B16: 100k directory smoke test | C16: Quality | D16: 1 | E16: P1 | F16: Not started
A17: 5.3b | B17: Full load test on temporary ADB | C17: Quality | D17: 3 | E17: P0 | F17: Not started
A18: 5.3c | B18: Load test re-run | C18: Quality | D18: 1 | E18: P0 | F18: Not started
A19: 5.4 | B19: Full WCAG 2.2 AA audit | C19: Quality | D19: 2 | E19: P0 | F19: Not started
A20: 5.4a | B20: First WCAG 2.2 pass | C20: Quality | D20: 0.5 | E20: P1 | F20: Not started
... A27: 6.3b | B27: Content import into PROD | C27: Content & adoption | D27: 1.5 | E27: P0 | F27: Not started
A28: 6.8 | B28: >= 3 partner orgs verified for pilot | C28: Content & adoption | D28: OAN | E28: P0 | F28: Not started
A29: 7.1a | B29: Core DPIA + RoPA (incl. antivirus risk) | C29: Compliance | D29: OAN | E29: P0 | F29: Not started
A30: 7.1b | B30: DPIA annex: AI assistant | C30: Compliance | D30: OAN | E30: P0 | F30: Not started
A31: 7.1c | B31: DPIA annex: channels | C31: Compliance | D31: OAN | E31: P0 | F31: Not started
A32: 7.1d | B32: DPIA annex: Careers feed | C32: Compliance | D32: OAN | E32: P0 | F32: Not started
A33: 7.2a | B33: DPAs: OCI, Google, LinkedIn, email | C33: Compliance | D33: OAN | E33: P0 | F33: Not started
A34: 7.2b | B34: DPA: GenAI provider | C34: Compliance | D34: OAN | E34: P0 | F34: Not started
A35: 7.2c | B35: DPAs: Slack, Meta | C35: Compliance | D35: OAN | E35: P0 | F35: Not started
A36: 7.3 | B36: Legal texts incl. partner, channel, HR notices | C36: Compliance | D36: OAN | E36: P0 | F36: Not started
A37: 7.4 | B37: Grievance officer, breach runbook | C37: Compliance | D37: OAN | E37: P0 | F37: Not started
A38: 7.5 | B38: Owners, access policy, Q6 + EXPERT/TRAINER confirmation | C38: Compliance | D38: OAN | E38: P0 | F38: Not started
A39: 8.0 | B39: Go-live gate (18 checks) | C39: Release | D39: 1.5 | E39: P0 | F39: Not started
A40: 8.1 | B40: Provision PROD + rehearsed deploy | C40: Release | D40: 1 | E40: P0 | F40: Not started
A41: 8.2 | B41: Seed chapters, assign attested admins | C41: Release | D41: 0.5 | E41: P0 | F41: Not started
A42: 8.3 | B42: Pilot: ~50 members, every staff role, >= 3 orgs | C42: Release | D42: OAN | E42: P0 | F42: Not started
A43: 8.4 | B43: Exit review kickoff | C43: Release | D43: OAN | E43: P0 | F43: Not started
A44: 8.5 | B44: Load legal texts v1 | C44: Release | D44: 0.25 | E44: P0 | F44: Not started
A45: 8.7 | B45: KPI baseline plan (go-live + 3 months) | C45: Release | D45: OAN | E45: P0 | F45: Not started
A46: 9.1 | B46: UAT plan by role and journey | C46: Acceptance | D46: 1.5 | E46: P0 | F46: Not started
A47: 9.2 | B47: Final UAT sign-off (G5) | C47: Acceptance | D47: 3 | E47: P0 | F47: Not started
A48: 9.2a | B48: Product-owner demo: W0-W2 | C48: Acceptance | D48: 1 | E48: P0 | F48: Not started
A49: 9.2b | B49: Product-owner demo: W3-W5 | C49: Acceptance | D49: 1 | E49: P0 | F49: Not started
A50: 9.2c | B50: Product-owner demo: W6 | C50: Acceptance | D50: 1 | E50: P0 | F50: Not started
A51: 9.3-9.5 | B51: Admin guide, member FAQ, runbook | C51: Acceptance | D51: 4.5 | E51: P0 | F51: Not started
A52: 9.6 | B52: Go-live checklist, rollback, smoke test | C52: Acceptance | D52: 0.5 | E52: P0 | F52: Not started
A53: 9.7 | B53: Hypercare (2 weeks) | C53: Acceptance | D53: 3 | E53: P0 | F53: Not started
A54: 9.8 | B54: Handover + v1.x backlog | C54: Acceptance | D54: 1 | E54: P0 | F54: Not started
A55: M.1 | B55: APEXLang 26.1 -> 26.2 metadata | C55: Migration | D55: 1.5 | E55: P0 | F55: Not started
A56: W0.16 | B56: Terms versions, deny-list, breached passwords | C56: W0 Auth & admin | D56: 0.75 | E56: P0 | F56: Not started
A57: W0.17 | B57: Health pages | C57: W0 Auth & admin | D57: 0.25 | E57: P0 | F57: Not started
... A158: W5.6 | B158: Hourly SLA job | C158: W5 Jobs & helpdesk | D158: 0.5 | E158: P2 | F158: Done

Sheet Delivery Board
A1: OAN Portal Delivery Board - 16 Sprints, 11 Gates (Plan V3.2, Iteration 9, 13 Oct 2026)
A2: Source: attached OAN-Delivery-Board-landscape.pdf. APEX Build Pack V1.1 (Q31) - APEX 26.1.5 (Q32) - no Oracle HR brokering (Q29) - no Oracle logos (Q30). Card status comes from task_plan.md in the GitHub repository.
A4: Board in numbers
A5: Sprints | B5: Gates | C5: Tracked tasks | D5: Dev estimate | E5: Done or authored offline | F5: Blocked | G5: Planned end of S15
A6: 16 | B6: 11 | C6: 154 | D6: 319.75 | E6: 70 | F6: 3 | G6: 28 May 2027
A7: S0-S15 | B7: incl. go-live 8.0 | C7: on the board | D7: person-days pd | E7: iteration 23 | F7: mostly on G0
A9: Sprints, S0-S15
A10: Sprint | B10: Window | C10: Phase | D10: Theme and scope | E10: Tasks | F10: Dev pd | G10: Gate(s)
A11: S0 | B11: 19-30 Oct 2026 | C11: SETUP | D11: Toolchain, spikes, migrations | E11: 21 | F11: 18.75 | G11: G0
A12: S1 | B12: 2-13 Nov 2026 | C12: BUILD | D12: First shared DB deploy | E12: 17 | F12: 49.25
A13: S2 | B13: 16-27 Nov 2026 | C13: BUILD | D13: DB tests, W0 auth + admin | E13: 18 | F13: 32.5 | G13: G1, G-RB
A14: S3 | B14: 30 Nov-11 Dec 2026 | C14: BUILD | D14: W0 onboarding, W1 shell | E14: 17 | F14: 27 | G14: G-AI
A15: S4 | B15: 14-25 Dec 2026 | C15: BUILD | D15: W2 profile + directory | E15: 5 | F15: 13
A16: S5 | B16: 28 Dec 2026-8 Jan 2027 | C16: BUILD | D16: W2 CV, privacy; demo 1 | E16: 10 | F16: 21.25
A17: S6 | B17: 11-22 Jan 2027 | C17: BUILD | D17: W3 content, W4 messaging | E17: 12 | F17: 26.25 | G17: G-CH
A18: S7 | B18: 25 Jan-5 Feb 2027 | C18: BUILD | D18: W4 channels, W5 orgs | E18: 6 | F18: 24.75 | G18: G-CF
A19: S8 | B19: 8-19 Feb 2027 | C19: BUILD | D19: W5 jobs, helpdesk, W6 experts; demo 2 | E19: 9 | F19: 22 | G19: G2
A20: S9 | B20: 22 Feb-5 Mar 2027 | C20: BUILD | D20: W6 groups, partners, mentoring | E20: 6 | F20: 18
A21: S10 | B21: 8-19 Mar 2027 | C21: BUILD | D21: W6 training, initiatives; demo 3; buffer | E21: 5 | F21: 13.25 | G21: G3
A22: S11 | B22: 22 Mar-2 Apr 2027 | C22: BUILD + DESCOPE | D22: W7 reports; descope lane | E22: 9 | F22: 26
A23: S12 | B23: 5-16 Apr 2027 | C23: HARDENING + UAT | D23: Load, WCAG, security, UAT | E23: 7 | F23: 18 | G23: G4, G5
A24: S13 | B24: 19-30 Apr 2027 | C24: GO-LIVE GATE | D24: Gate 8.0, PROD release | E24: 7 | F24: 5.75 | G24: 8.0
A25: S14 | B25: 3-14 May 2027 | C25: PILOT | D25: Pilot ~50 members, every staff role, >= 3 orgs | E25: 1 | F25: 0
A26: S15 | B26: 17-28 May 2027 | C26: HYPERCARE | D26: Hypercare + handover | E26: 4 | F26: 4
A27: Total | E27: =SUM(E11:E26) -> 154 | F27: =ROUND(SUM(F11:F26),2) -> 319.75
A29: Progress by workstream (iteration 23)
A30: Workstream | B30: Done | C30: Total | D30: Progress
A31: WS0 Environment | B31: 11 | C31: 23 | D31: =B31/C31 -> 0.47826087
A32: WS1 Database | B32: 15 | C32: 20 | D32: =B32/C32 -> 0.75
A33: W0 Auth & admin | B33: 9 | C33: 22 | D33: =B33/C33 -> 0.40909091
A34: W1 Shell & Home | B34: 3 | C34: 3 | D34: =B34/C34 -> 1
A35: W2 Profile & directory | B35: 9 | C35: 11 | D35: =B35/C35 -> 0.81818182
A36: W3 Insights & events | B36: 5 | C36: 6 | D36: =B36/C36 -> 0.83333333
A37: W4 Conversations | B37: 4 | C37: 6 | D37: =B37/C37 -> 0.66666667
A38: W5 Opportunities | B38: 5 | C38: 7 | D38: =B38/C38 -> 0.71428571
A39: All workstreams | B39: =SUM(B31:B38) -> 61 | C39: =SUM(C31:C38) -> 98 | D39: =B39/C39 -> 0.62244898
A41: Board status legend (left border colour on the attached board)
A42: Status | B42: Meaning | C42: On the attached board
A43: Not started | B43: Not begun; open in a future sprint. | G43: Grey
A44: In progress | B44: Actively being worked this sprint. | G44: Amber
A45: Authored offline (validated, not live) | B45: Written and validated locally; not yet deployed. | G45: Blue
A46: Blocked | B46: Cannot proceed; mostly waiting on G0 (ADMIN bootstrap, OAuth client). | G46: Red
A47: Gated by Build Option | B47: Built with the Build Option on in DEV; switched on in PROD only after DPIA sign-off and the external gate. | G47: Purple
A48: Done | B48: Complete and accepted. | G48: Green
A50: - Estimates are developer person-days (pd) before the 20% contingency.
A51: - Tiers P0-P4 come from docs/05-flow-priority.md: P0 and P1 are never cut; the S11 descope lane cuts from P4 upward.
A52: - Gated items are built with their Build Option on in DEV only, and switched on in PROD only after the DPIA sign-off and the external gate.
A53: - Planned end of S15 is 28 May 2027.

Sheet Gate Checklist
A1: Gate Checklist - 11 Gates incl. Go-Live 8.0
A2: Every gate, its due date, its status and the condition that must be met. Gates are explicit decision points: no gate is passed without its condition.
A4: Gate | B4: Due | C4: Status | D4: Condition
A5: G0 | B5: End S0 - 19-30 Oct | C5: In progress | D5: Done: toolchain, dev ADB aiatp on APEX 26.1.5 (Q32), ADMIN bootstrap, install, utPLSQL, spikes (13 Oct); app 200 live on dev with 51 pages (14 Oct). Open: Google OAuth set aside (Q33), staffing decision.
A6: G1 | B6: End S2 - 16-27 Nov | C6: Pending | D6: Content inventory + owner; product owner signs off the Must/Should/Could AC list.
A7: G-RB | B7: End S2 - 16-27 Nov | C7: Pending | D7: Re-baseline: S1-S2 velocity and offline-rework actuals vs plan; invoke descope lane if < 20 pd/sprint.
A8: G-AI | B8: End S3 - 30 Nov-11 Dec | C8: Pending | D8: AI_ASSISTANT DPIA annex + GenAI DPA signed.
A9: G-CH | B9: End S6 - 11-22 Jan | C9: Pending | D9: Slack app, WhatsApp Business + templates, Slack/Meta DPAs, CHANNELS DPIA annex.
A10: G-CF | B10: End S7 - 25 Jan-5 Feb | C10: Pending | D10: CAREERS_FEED DPIA annex + feed terms.
A11: G2 | B11: End S8 - 8-19 Feb | C11: Pending | D11: Region decided; temporary 100k load-test ADB booked.
A12: G3 | B12: End S10 - 8-19 Mar | C12: Pending | D12: All staff-role holders named with IdP + 2-step verification; >= 3 pilot orgs verified.
A13: G4 | B13: End S12 - 5-16 Apr | C13: Pending | D13: Legal texts, privacy contact, compliance workstream complete.
A14: G5 | B14: End S12 - 5-16 Apr | C14: Pending | D14: Final UAT (J-01..J-21 regression) signed by the product owner.
A15: 8.0 | B15: S13 - 19-30 Apr | C15: Pending | D15: Go-live gate: 18 checks incl. DPIA per option, secrets, ORDS exposure, every Must AC.
A17: Gate groups
A18: Build-option gates (G-AI, G-CH, G-CF) | B18: Each gated Build Option needs its own DPIA annex and its external agreement signed before it is switched on in PROD.
A19: Re-baseline gate (G-RB) | B19: Invokes the descope lane if measured velocity falls below 20 pd per sprint across S1-S2.
A20: Release gates (G4, G5, 8.0) | B20: Compliance complete, final UAT signed, then the 18-check go-live gate.
A21: Post-go-live (S14 pilot, S15 hypercare) | B21: Pilot with ~50 members covering every staff role and >= 3 partner organisations, then two weeks of hypercare and handover.

Sheet Kanban Board
A1: Delivery Kanban - OAN Portal Build Backlog by Status
A2: One card per work item, in the six status columns of the attached delivery board. Columns run Not started > In progress > Authored offline > Blocked > Gated > Done. Full card list on the Board Tasks tab.
A4: =COUNTIF('Board Tasks'!$F$3:$F$156,"Not started")&" Not started" -> 65 Not started | E4: =COUNTIF('Board Tasks'!$F$3:$F$156,"In progress")&" In progress" -> 13 In progress | I4: =COUNTIF('Board Tasks'!$F$3:$F$156,"Authored offline (validated, not live)")&" Authored offline (validated, not live)" -> 9 Authored offline (validated, not live) | M4: =COUNTIF('Board Tasks'!$F$3:$F$156,"Blocked")&" Blocked" -> 3 Blocked | Q4: =COUNTIF('Board Tasks'!$F$3:$F$156,"Gated by Build Option")&" Gated by Build Option" -> 3 Gated by Build Option | U4: =COUNTIF('Board Tasks'!$F$3:$F$156,"Done")&" Done" -> 59 Done
A5: =ROUND(SUMIF('Board Tasks'!$F$3:$F$156,"Not started",'Board Tasks'!$D$3:$D$156),2)&" pd" -> 100 pd | E5: =ROUND(SUMIF('Board Tasks'!$F$3:$F$156,"In progress",'Board Tasks'!$D$3:$D$156),2)&" pd" -> 43.75 pd | I5: =ROUND(SUMIF('Board Tasks'!$F$3:$F$156,"Authored offline (validated, not live)",'Board Tasks'!$D$3:$D$156),2)&" pd" -> 17.75 pd | M5: =ROUND(SUMIF('Board Tasks'!$F$3:$F$156,"Blocked",'Board Tasks'!$D$3:$D$156),2)&" pd" -> 3 pd | Q5: =ROUND(SUMIF('Board Tasks'!$F$3:$F$156,"Gated by Build Option",'Board Tasks'!$D$3:$D$156),2)&" pd" -> 15 pd | U5: =ROUND(SUMIF('Board Tasks'!$F$3:$F$156,"Done",'Board Tasks'!$D$3:$D$156),2)&" pd" -> 137 pd
A6: 0.16a 1.5 pd | E6: 0.15 1.0 pd | I6: 1.32 0.5 pd | M6: 0.12 1.0 pd | Q6: W0.9 3.0 pd | U6: 0.1 0.5 pd
A7: Liquibase changelog (forward-only) | E7: Secrets register (all secrets, owners, rotation) | I7: OAN_LU_CODE intents with live_yn | M7: Spike: social sign-in, switch in session, re-auth | Q7: AI assistant (read-only, opt-in) | U7: Node, JDK 21, SQLcl 26.2 installed
A8: Environment | P0 | E8: Environment | P0 | I8: Database | P1 | M8: Environment | P0 | Q8: W0 Auth & admin | P4 | U8: Environment | P0
A9: 0.16c 0.5 pd | E9: 0.9 2.5 pd | I9: M.2 3.5 pd | M9: 0.17 1.5 pd | Q9: W4.4a 6.0 pd | U9: 0.10 0.25 pd
A10: Scratch-schema rebuild each sprint | E10: CI: base-table scan, authz, utPLSQL, gitleaks, validate, page registry, brand | I10: Groups refactor: forums -> groups / posts / comments | M10: Spike: webhook HMAC + async job < 1s | Q10: Slack channel | U10: Spike: APEX version on dev and PROD
A11: Environment | P0 | E11: Environment | P0 | I11: Migration | P1 | M11: Environment | P4 | Q11: W4 Messaging & channels | P4 | U11: Environment | P0
A12: 0.18 0.5 pd | E12: 1.23 1.5 pd | I12: W0.10 2.0 pd | M12: 0.6 0.5 pd | Q12: W4.4b 6.0 pd | U12: 0.11 1.0 pd
A13: Spike: APEX GenAI service | E13: Jobs package (fix failure link -> 1075) | I13: Approval queue + application review | M13: Google OIDC client | Q13: WhatsApp channel + channel settings (Page 43) | U13: Spike: two-schema calls incl. ORDS
A14: Environment | P4 | E14: Database | P0 | I14: W0 Auth & admin | P0 | M14: Environment | P0 | Q14: W4 Messaging & channels | P4 | U14: Environment | P0
A15: 0.19 OAN | E15: 1.26 4.0 pd | I15: W0.11 3.0 pd | U15: 0.13 0.5 pd
A16: Procure Slack app, WhatsApp Business | E16: utPLSQL suites (R01, R16, R19/20, R26, secrets) | I16: Members, staff roles, scopes | U16: Spike: PBKDF2 210k under load
A17: Environment | P4 | E17: Database | P0 | I17: W0 Auth & admin | P0 | U17: Environment | P0
A18: 0.1b 1.0 pd | E18: 1.28 2.5 pd | I18: W0.12 1.5 pd | U18: 0.14 0.5 pd
A19: Local Oracle DB Free + utPLSQL (optional) | E19: Synthetic data: 100k profiles, 1M posts, 20k jobs | I19: Chapters + chapter requests | U19: Spike: Oracle Text on ADB
A20: Environment | P4 | E20: Database | P0 | I20: W0 Auth & admin | P0 | U20: Environment | P0
A21: 0.20 1.0 pd | E21: W0.15 2.0 pd | I21: W0.13 2.0 pd | U21: 0.16b 0.75 pd
A22: ORDS install: OAN_API schema, channel modules | E22: Audit log, report modal, my decisions | I22: Lookups / taxonomy admin | U22: Deploy wrapper + live validate gate
A23: Environment | P4 | E23: W0 Auth & admin | P0 | I23: W0 Auth & admin | P0 | U23: Environment | P0
A24: 0.7 0.5 pd | E24: W0.18 7.5 pd | I24: W0.14 2.5 pd | U24: 0.2 0.5 pd
A25: OCI Email Delivery + APEX SMTP | E25: Shared components + security baseline | I25: Moderation queue + appeals | U25: Dev ADB (APEX 26.1.5, Q32), synthetic data
A26: Environment | P0 | E26: W0 Auth & admin | P0 | I26: W0 Auth & admin | P0 | U26: Environment | P0
... A32: Quality | P0 | E32: W2 Profile & directory | P0 | I32: W0 Auth & admin | P0 | U32: Environment | P0
A33: 5.10 3.0 pd | E33: W3.5 5.0 pd | U33: 0.5 0.25 pd
A34: J-01..J-21 end-to-end regression | E34: Library moderation, import, events admin | U34: Git repo, layout, .gitignore
A35: Quality | P0 | E35: W3 Content & events | P1 | U35: Environment | P0
A36: 5.2 3.0 pd | E36: W5.1 4.5 pd | U36: 0.8 0.25 pd
A37: Security test (ZAP, bypass, leaks) | E37: Organisations: application, verification (Pages 55, 1025) | U37: utPLSQL on dev
A38: Quality | P0 | E38: W5 Jobs & helpdesk | P2 | U38: Environment | P0
A39: 5.3a 1.0 pd | E39: W5.7 0.75 pd | U39: 1.1-1.5 7.25 pd
A40: 100k directory smoke test | E40: Careers deep-links (feed gated, G-CF) | U40: DDL: identity, profile, chapters, content, ops
A41: Quality | P1 | E41: W5 Jobs & helpdesk | P2 | U41: Database | P0
A42: 5.3b 3.0 pd | E42: W6.1 5.0 pd | U42: 1.14-1.22 15.0 pd
A43: Full load test on temporary ADB | E43: Groups governance, reactions, stories, private search | U43: Registration, profile, taxonomy, library, files, groups, moderation, notify, privacy
A44: Quality | P0 | E44: W6 Community & partners | P1 | U44: Database | P0
A45: 5.3c 1.0 pd | U45: 1.24 2.0 pd
A46: Load test re-run | U46: Text/search split (search_body, directory index)
A47: Quality | P0 | U47: Database | P1
A48: + 51 more on the Board Tasks tab | U48: + 47 more on the Board Tasks tab
A51: How this board works
A52: - Board totals: 154 tracked tasks and 319.75 pd of development estimate across the 16 sprints S0-S15.
A53: - 31 cards are Done or Authored offline (validated, not live); 6 are Blocked, mostly waiting on G0 (ADMIN bootstrap and the Google OAuth client).
A54: - Gated cards are built with their Build Option on in DEV only, and switched on in PROD only after their DPIA annex and external agreement are signed.
A55: - Estimates are developer person-days before the 20% contingency. P0 and P1 are never cut; the S11 descope lane cuts from P4 upward.
A56: - The Kanban Dashboard tab counts these cards live; the Delivery Board tab carries the sprint and gate structure.

Sheet Kanban Dashboard
A1: Kanban Dashboard - Board Flow, Effort and Priority
A2: Live from the Board Tasks tab. Sprint and gate structure sits on the Delivery Board tab; capacity and velocity on the Sprint Planner Dashboard tab.
A4: Items on board | B4: Dev estimate (pd) | C4: Done | D4: Authored offline | E4: In progress | F4: Blocked | G4: Gated | H4: Not started
A5: =COUNTA('Board Tasks'!$A$3:$A$156) -> 153 | B5: =ROUND(SUM('Board Tasks'!$D$3:$D$156),2) -> 316.5 | C5: =COUNTIF('Board Tasks'!$F$3:$F$156,"Done") -> 59 | D5: =COUNTIF('Board Tasks'!$F$3:$F$156,"Authored offline (validated, not live)") -> 9 | E5: =COUNTIF('Board Tasks'!$F$3:$F$156,"In progress") -> 13 | F5: =COUNTIF('Board Tasks'!$F$3:$F$156,"Blocked") -> 3 | G5: =COUNTIF('Board Tasks'!$F$3:$F$156,"Gated by Build Option") -> 3 | H5: =COUNTIF('Board Tasks'!$F$3:$F$156,"Not started") -> 65
A7: 1. Cards and effort by status
A8: Status | B8: Cards | C8: Dev pd | D8: % of pd
A9: Not started | B9: =COUNTIF('Board Tasks'!$F$3:$F$156,"Not started") -> 65 | C9: =ROUND(SUMIF('Board Tasks'!$F$3:$F$156,"Not started",'Board Tasks'!$D$3:$D$156),2) -> 100 | D9: =IFERROR(C9/SUM($C$9:$C$14),0) -> 0.31595577
A10: In progress | B10: =COUNTIF('Board Tasks'!$F$3:$F$156,"In progress") -> 13 | C10: =ROUND(SUMIF('Board Tasks'!$F$3:$F$156,"In progress",'Board Tasks'!$D$3:$D$156),2) -> 43.75 | D10: =IFERROR(C10/SUM($C$9:$C$14),0) -> 0.13823065
A11: Authored offline (validated, not live) | B11: =COUNTIF('Board Tasks'!$F$3:$F$156,"Authored offline (validated, not live)") -> 9 | C11: =ROUND(SUMIF('Board Tasks'!$F$3:$F$156,"Authored offline (validated, not live)",'Board Tasks'!$D$3:$D$156),2) -> 17.75 | D11: =IFERROR(C11/SUM($C$9:$C$14),0) -> 0.056082148
A12: Blocked | B12: =COUNTIF('Board Tasks'!$F$3:$F$156,"Blocked") -> 3 | C12: =ROUND(SUMIF('Board Tasks'!$F$3:$F$156,"Blocked",'Board Tasks'!$D$3:$D$156),2) -> 3 | D12: =IFERROR(C12/SUM($C$9:$C$14),0) -> 0.009478673
A13: Gated by Build Option | B13: =COUNTIF('Board Tasks'!$F$3:$F$156,"Gated by Build Option") -> 3 | C13: =ROUND(SUMIF('Board Tasks'!$F$3:$F$156,"Gated by Build Option",'Board Tasks'!$D$3:$D$156),2) -> 15 | D13: =IFERROR(C13/SUM($C$9:$C$14),0) -> 0.047393365
A14: Done | B14: =COUNTIF('Board Tasks'!$F$3:$F$156,"Done") -> 59 | C14: =ROUND(SUMIF('Board Tasks'!$F$3:$F$156,"Done",'Board Tasks'!$D$3:$D$156),2) -> 137 | D14: =IFERROR(C14/SUM($C$9:$C$14),0) -> 0.4328594
A16: 2. Effort by category
A17: Category | B17: Cards | C17: Dev pd
A18: Environment | B18: =COUNTIF('Board Tasks'!$C$3:$C$156,"Environment") -> 23 | C18: =ROUND(SUMIF('Board Tasks'!$C$3:$C$156,"Environment",'Board Tasks'!$D$3:$D$156),2) -> 17.5
A19: Database | B19: =COUNTIF('Board Tasks'!$C$3:$C$156,"Database") -> 20 | C19: =ROUND(SUMIF('Board Tasks'!$C$3:$C$156,"Database",'Board Tasks'!$D$3:$D$156),2) -> 57
A20: Quality | B20: =COUNTIF('Board Tasks'!$C$3:$C$156,"Quality") -> 13 | C20: =ROUND(SUMIF('Board Tasks'!$C$3:$C$156,"Quality",'Board Tasks'!$D$3:$D$156),2) -> 28.5
A21: Content & adoption | B21: =COUNTIF('Board Tasks'!$C$3:$C$156,"Content & adoption") -> 3 | C21: =ROUND(SUMIF('Board Tasks'!$C$3:$C$156,"Content & adoption",'Board Tasks'!$D$3:$D$156),2) -> 2
A22: Compliance | B22: =COUNTIF('Board Tasks'!$C$3:$C$156,"Compliance") -> 10 | C22: =ROUND(SUMIF('Board Tasks'!$C$3:$C$156,"Compliance",'Board Tasks'!$D$3:$D$156),2) -> 0
A23: Release | B23: =COUNTIF('Board Tasks'!$C$3:$C$156,"Release") -> 7 | C23: =ROUND(SUMIF('Board Tasks'!$C$3:$C$156,"Release",'Board Tasks'!$D$3:$D$156),2) -> 3.25
A24: Acceptance | B24: =COUNTIF('Board Tasks'!$C$3:$C$156,"Acceptance") -> 9 | C24: =ROUND(SUMIF('Board Tasks'!$C$3:$C$156,"Acceptance",'Board Tasks'!$D$3:$D$156),2) -> 16.5
A25: Migration | B25: =COUNTIF('Board Tasks'!$C$3:$C$156,"Migration") -> 2 | C25: =ROUND(SUMIF('Board Tasks'!$C$3:$C$156,"Migration",'Board Tasks'!$D$3:$D$156),2) -> 5
A26: W0 Auth & admin | B26: =COUNTIF('Board Tasks'!$C$3:$C$156,"W0 Auth & admin") -> 22 | C26: =ROUND(SUMIF('Board Tasks'!$C$3:$C$156,"W0 Auth & admin",'Board Tasks'!$D$3:$D$156),2) -> 43
A27: W1 Shell | B27: =COUNTIF('Board Tasks'!$C$3:$C$156,"W1 Shell") -> 3 | C27: =ROUND(SUMIF('Board Tasks'!$C$3:$C$156,"W1 Shell",'Board Tasks'!$D$3:$D$156),2) -> 5
A28: W2 Profile & directory | B28: =COUNTIF('Board Tasks'!$C$3:$C$156,"W2 Profile & directory") -> 11 | C28: =ROUND(SUMIF('Board Tasks'!$C$3:$C$156,"W2 Profile & directory",'Board Tasks'!$D$3:$D$156),2) -> 30.75
A29: W3 Content & events | B29: =COUNTIF('Board Tasks'!$C$3:$C$156,"W3 Content & events") -> 6 | C29: =ROUND(SUMIF('Board Tasks'!$C$3:$C$156,"W3 Content & events",'Board Tasks'!$D$3:$D$156),2) -> 16.75
A30: W4 Messaging & channels | B30: =COUNTIF('Board Tasks'!$C$3:$C$156,"W4 Messaging & channels") -> 6 | C30: =ROUND(SUMIF('Board Tasks'!$C$3:$C$156,"W4 Messaging & channels",'Board Tasks'!$D$3:$D$156),2) -> 29.25
A31: W5 Jobs & helpdesk | B31: =COUNTIF('Board Tasks'!$C$3:$C$156,"W5 Jobs & helpdesk") -> 5 | C31: =ROUND(SUMIF('Board Tasks'!$C$3:$C$156,"W5 Jobs & helpdesk",'Board Tasks'!$D$3:$D$156),2) -> 17.75
A32: W6 Community & partners | B32: =COUNTIF('Board Tasks'!$C$3:$C$156,"W6 Community & partners") -> 9 | C32: =ROUND(SUMIF('Board Tasks'!$C$3:$C$156,"W6 Community & partners",'Board Tasks'!$D$3:$D$156),2) -> 36.75
A33: W7 Reporting | B33: =COUNTIF('Board Tasks'!$C$3:$C$156,"W7 Reporting") -> 3 | C33: =ROUND(SUMIF('Board Tasks'!$C$3:$C$156,"W7 Reporting",'Board Tasks'!$D$3:$D$156),2) -> 7.5
A35: 3. Cards by priority tier
A36: Priority | B36: Cards | C36: Dev pd | D36: Meaning
A37: P0 | B37: =COUNTIF('Board Tasks'!$E$3:$E$156,"P0") -> 98 | C37: =ROUND(SUMIF('Board Tasks'!$E$3:$E$156,"P0",'Board Tasks'!$D$3:$D$156),2) -> 164.75 | D37: Critical path - never cut
A38: P1 | B38: =COUNTIF('Board Tasks'!$E$3:$E$156,"P1") -> 30 | C38: =ROUND(SUMIF('Board Tasks'!$E$3:$E$156,"P1",'Board Tasks'!$D$3:$D$156),2) -> 75.75 | D38: Never cut
A39: P2 | B39: =COUNTIF('Board Tasks'!$E$3:$E$156,"P2") -> 8 | C39: =ROUND(SUMIF('Board Tasks'!$E$3:$E$156,"P2",'Board Tasks'!$D$3:$D$156),2) -> 25.25 | D39: Committed
A40: P3 | B40: =COUNTIF('Board Tasks'!$E$3:$E$156,"P3") -> 6 | C40: =ROUND(SUMIF('Board Tasks'!$E$3:$E$156,"P3",'Board Tasks'!$D$3:$D$156),2) -> 26.75 | D40: Committed - first to flex
A41: P4 | B41: =COUNTIF('Board Tasks'!$E$3:$E$156,"P4") -> 10 | C41: =ROUND(SUMIF('Board Tasks'!$E$3:$E$156,"P4",'Board Tasks'!$D$3:$D$156),2) -> 24 | D41: Descope lane - cut first

Sheet Sprint Planner Dashboard
A1: Sprint Planner Dashboard - Attached Capacity & Performance Charts
A2: Ports the live charts from the attached 'Sprint Capacity Planner & Performance Tracker.xlsx' into this plan. Series are linked to the Sprint Capacity Planner and Sprint Performance Tracker tabs.
A4: Attachment
A5: Attached source | C5: Sprint Capacity Planner & Performance Tracker.xlsx
A6: How it is attached | C6: Its Capacity Planner, Performance Tracker and dashboard charts are integrated into this workbook (Sprint Capacity Planner, Sprint Performance Tracker and Sprint Planner Dashboard tabs).
A7: Refresh | C7: Edit inputs on the Sprint Capacity Planner tab; the tracker formulas and these charts recalculate automatically.
A9: 1. Commitment vs delivery by sprint (Performance Tracker)
A10: Sprint | B10: Committed (SP) | C10: Delivered (SP) | D10: Completion % | E10: 3-sprint avg
A11: ='Sprint Performance Tracker'!A6 -> Sprint 1 | B11: ='Sprint Performance Tracker'!G6 -> 32 | C11: ='Sprint Performance Tracker'!H6 -> 27 | D11: ='Sprint Performance Tracker'!I6 -> 0.84375 | E11: ='Sprint Performance Tracker'!K6 -> 27
A12: ='Sprint Performance Tracker'!A7 -> Sprint 2 | B12: ='Sprint Performance Tracker'!G7 -> 34 | C12: ='Sprint Performance Tracker'!H7 -> 30 | D12: ='Sprint Performance Tracker'!I7 -> 0.88235294 | E12: ='Sprint Performance Tracker'!K7 -> 28.5
A13: ='Sprint Performance Tracker'!A8 -> Sprint 3 | B13: ='Sprint Performance Tracker'!G8 -> 30 | C13: ='Sprint Performance Tracker'!H8 -> 25 | D13: ='Sprint Performance Tracker'!I8 -> 0.83333333 | E13: ='Sprint Performance Tracker'!K8 -> 27.333333
A14: ='Sprint Performance Tracker'!A9 -> Sprint 4 | B14: ='Sprint Performance Tracker'!G9 -> 36 | C14: ='Sprint Performance Tracker'!H9 -> 33 | D14: ='Sprint Performance Tracker'!I9 -> 0.91666667 | E14: ='Sprint Performance Tracker'!K9 -> 29.333333
A15: ='Sprint Performance Tracker'!A10 -> Sprint 5 | B15: ='Sprint Performance Tracker'!G10 -> 33 | C15: ='Sprint Performance Tracker'!H10 -> 29 | D15: ='Sprint Performance Tracker'!I10 -> 0.87878788 | E15: ='Sprint Performance Tracker'!K10 -> 29
A16: ='Sprint Performance Tracker'!A11 -> Sprint 6 | B16: ='Sprint Performance Tracker'!G11 -> 38 | C16: ='Sprint Performance Tracker'!H11 -> 35 | D16: ='Sprint Performance Tracker'!I11 -> 0.92105263 | E16: ='Sprint Performance Tracker'!K11 -> 32.333333
A17: ='Sprint Performance Tracker'!A12 -> Sprint 7 | B17: ='Sprint Performance Tracker'!G12 -> 35 | C17: ='Sprint Performance Tracker'!H12 -> 33 | D17: ='Sprint Performance Tracker'!I12 -> 0.94285714 | E17: ='Sprint Performance Tracker'!K12 -> 32.333333
A18: ='Sprint Performance Tracker'!A13 -> Sprint 8 | B18: ='Sprint Performance Tracker'!G13 -> 40 | C18: ='Sprint Performance Tracker'!H13 -> 37 | D18: ='Sprint Performance Tracker'!I13 -> 0.925 | E18: ='Sprint Performance Tracker'!K13 -> 35
A19: ='Sprint Performance Tracker'!A14 -> Sprint 9 | B19: ='Sprint Performance Tracker'!G14 -> 37 | C19: ='Sprint Performance Tracker'!H14 -> 35 | D19: ='Sprint Performance Tracker'!I14 -> 0.94594595 | E19: ='Sprint Performance Tracker'!K14 -> 35
A20: ='Sprint Performance Tracker'!A15 -> Sprint 10 | B20: ='Sprint Performance Tracker'!G15 -> 42 | C20: ='Sprint Performance Tracker'!H15 -> 39 | D20: ='Sprint Performance Tracker'!I15 -> 0.92857143 | E20: ='Sprint Performance Tracker'!K15 -> 37
A21: ='Sprint Performance Tracker'!A16 -> Sprint 11 | B21: ='Sprint Performance Tracker'!G16 -> 39 | C21: ='Sprint Performance Tracker'!H16 -> 37 | D21: ='Sprint Performance Tracker'!I16 -> 0.94871795 | E21: ='Sprint Performance Tracker'!K16 -> 37
A22: ='Sprint Performance Tracker'!A17 -> Sprint 12 | B22: ='Sprint Performance Tracker'!G17 -> 44 | C22: ='Sprint Performance Tracker'!H17 -> 42 | D22: ='Sprint Performance Tracker'!I17 -> 0.95454545 | E22: ='Sprint Performance Tracker'!K17 -> 39.333333
A24: 2. Capacity and forecast (Capacity Planner + Tracker)
A25: Current sprint capacity (SP) | B25: Risk-adjusted capacity (SP) | C25: Recommended commitment (SP) | D25: Average completion rate | E25: Next sprint forecast (SP)
A26: ='Sprint Capacity Planner'!B24 -> 53.75 | B26: ='Sprint Capacity Planner'!B25 -> 48.375 | C26: ='Sprint Capacity Planner'!B27 -> 48.375 | D26: =AVERAGE(D11:D22) -> 0.91013178 | E26: =FORECAST(13,C11:C22,'Sprint Performance Tracker'!$M$6:$M$17) -> 41.636364
A28: 3. Resource story-point capacity - current sprint (Capacity Planner)
A29: Resource | B29: Role | C29: Hours available | D29: Story-point capacity | E29: Allocation %
A30: Resource 1 | B30: ='Sprint Capacity Planner'!B$4 -> Product Owner | C30: ='Sprint Capacity Planner'!B19 -> 23 | D30: ='Sprint Capacity Planner'!B22 -> 2.875 | E30: ='Sprint Capacity Planner'!B15 -> 0.5
A31: Resource 2 | B31: ='Sprint Capacity Planner'!C$4 -> Scrum Master / Delivery Lead | C31: ='Sprint Capacity Planner'!C19 -> 23 | D31: ='Sprint Capacity Planner'!C22 -> 2.875 | E31: ='Sprint Capacity Planner'!C15 -> 0.5
A32: Resource 3 | B32: ='Sprint Capacity Planner'!D$4 -> UX Lead | C32: ='Sprint Capacity Planner'!D19 -> 63 | D32: ='Sprint Capacity Planner'!D22 -> 7.875 | E32: ='Sprint Capacity Planner'!D15 -> 1
A33: Resource 4 | B33: ='Sprint Capacity Planner'!E$4 -> UI / Visual Designer | C33: ='Sprint Capacity Planner'!E19 -> 63 | D33: ='Sprint Capacity Planner'!E22 -> 7.875 | E33: ='Sprint Capacity Planner'!E15 -> 1
A34: Resource 5 | B34: ='Sprint Capacity Planner'!F$4 -> Design Systems / Front-end | C34: ='Sprint Capacity Planner'!F19 -> 63 | D34: ='Sprint Capacity Planner'!F22 -> 7.875 | E34: ='Sprint Capacity Planner'!F15 -> 1
A35: Resource 6 | B35: ='Sprint Capacity Planner'!G$4 -> Back-end Engineer | C35: ='Sprint Capacity Planner'!G19 -> 63 | D35: ='Sprint Capacity Planner'!G22 -> 7.875 | E35: ='Sprint Capacity Planner'!G15 -> 1
A36: Resource 7 | B36: ='Sprint Capacity Planner'!H$4 -> Solution Architect | C36: ='Sprint Capacity Planner'!H19 -> 23 | D36: ='Sprint Capacity Planner'!H22 -> 2.875 | E36: ='Sprint Capacity Planner'!H15 -> 0.5
A37: Resource 8 | B37: ='Sprint Capacity Planner'!I$4 -> Accessibility / QA Lead | C37: ='Sprint Capacity Planner'!I19 -> 63 | D37: ='Sprint Capacity Planner'!I22 -> 7.875 | E37: ='Sprint Capacity Planner'!I15 -> 1
A38: Resource 9 | B38: ='Sprint Capacity Planner'!J$4 -> Content Strategist | C38: ='Sprint Capacity Planner'!J19 -> 23 | D38: ='Sprint Capacity Planner'!J22 -> 2.875 | E38: ='Sprint Capacity Planner'!J15 -> 0.5
A39: Resource 10 | B39: ='Sprint Capacity Planner'!K$4 -> Change & Comms Lead | C39: ='Sprint Capacity Planner'!K19 -> 23 | D39: ='Sprint Capacity Planner'!K22 -> 2.875 | E39: ='Sprint Capacity Planner'!K15 -> 0.5

Sheet Status Report
A1: Project Status Report - OAN Portal (as of 15 October 2026 (iteration 23))
A2: Oracle APEX application 200 on Autonomous Database - Plan v3.2 - APEX Build Pack v1.1 - development environment only. Source: OAN-Project-Status-Report.pdf.
A4: Summary
A5: The portal is well ahead of plan. Sprint S0 formally starts on 19 October, yet the database platform and waves W0 to W5 already run on the dev environment: sign-in and onboarding, the member shell and Home, profiles, directory and CV, insights and events, conversations and notifications, opportunities, referrals, helpdesk and skills in demand, plus company registration for partners and other employers.
A6: Every change is validated, tested on the database and pushed to GitHub, where CI runs on each push.
A7: MAIN RISK: admin pages cannot be tested end to end because staff roles need Google or LinkedIn sign-in (NFR-01) and Google sign-in is set aside (Q33). Email delivery (task 0.7) is not set up, so emails are queued but not delivered on dev. Slack and WhatsApp are built but stay off until gate G-CH.
A9: Progress at a glance
A10: APEX pages live on dev | B10: Database tests passing | C10: Test suites | D10: Person-days of plan done
A11: 73 | B11: 147 | C11: 16 | D11: 140
A13: Person-days of plan done | B13: Plan person-days before contingency | C13: Progress vs plan | D13: Blocked or gated | E13: Tasks on board
A14: 140 | B14: 320 | C14: 0.4375 | D14: 6 | E14: 154
A16: Board status distribution (154 tracked tasks)
A17: Status | B17: Tasks | C17: % of board | D17: Source
A18: Done | B18: 61 | C18: =B18/SUM($B$18:$B$23) -> 0.3961039 | D18: Status report / board (iter 23)
A19: In progress | B19: 13 | C19: =B19/SUM($B$18:$B$23) -> 0.084415584 | D19: Status report / board (iter 23)
A20: Authored, untested | B20: 9 | C20: =B20/SUM($B$18:$B$23) -> 0.058441558 | D20: Status report / board (iter 23)
A21: Blocked | B21: 3 | C21: =B21/SUM($B$18:$B$23) -> 0.019480519 | D21: Status report / board (iter 23)
A22: Gated by build option | B22: 3 | C22: =B22/SUM($B$18:$B$23) -> 0.019480519 | D22: Status report / board (iter 23)
A23: Not started | B23: 65 | C23: =B23/SUM($B$18:$B$23) -> 0.42207792 | D23: Status report / board (iter 23)
A24: Total | B24: =SUM(B18:B23) -> 154 | C24: =SUM(C18:C23) -> 1
A26: Progress by workstream
A27: Workstream | B27: Status | C27: What is in place
A28: WS0 Environment | B28: 11 of 23 done | C28: Dev ADB on APEX 26.1.5, ADMIN bootstrap, utPLSQL, spikes. Blocked: Google client, social sign-in spike, email delivery.
A29: WS1 Database | B29: 15 of 20 done | C29: 100 tables, 126 secure views, 39 packages; personal-data registry with retention rules; staff scopes; job run locks; synthetic data.
A30: W0 Auth & admin | B30: 9 of 22 done | C30: Sign-in, registration, onboarding chat, legal, identity confirmation; admin pages built but untested (no admin login).
A31: W1 Shell & Home | B31: 3 of 3 done | C31: Rail, profile card, search, notifications badge; Home with letters, upcoming events and What's new.
A32: W2 Profile & directory | B32: 9 of 11 done | C32: Directory index, cards with Follow and Message, profiles, CV sections, sharing and printing, work profile, introductions, recommendations, reminders.
A33: W3 Insights & events | B33: 5 of 6 done | C33: Insights and perspectives with saves; events with registration, waitlist, calendar file, reminders and check-in.
A34: W4 Conversations | B34: 4 of 6 done | C34: Conversations with search and polling, notification settings, unsubscribe, Help Me Connect. Slack and WhatsApp built, gated (G-CH).
A35: W5 Opportunities | B35: 5 of 7 done | C35: Opportunities, applications with optional CV, referrals, helpdesk, skills in demand; company registration and workspace.
A36: W6-W7, quality, release | B36: next | C36: Community groups, experts, mentoring, training, partner talent requests; then administration and hardening.
A38: Decisions and actions needed
A39: Item | B39: Impact | C39: Owner | D39: Status
A40: Google OAuth client, or a dev-only admin login | B40: Blocks testing of admin pages, company verification and moderation (NFR-01) | C40: OAN / product owner | D40: Open
A41: OCI Email Delivery for dev (task 0.7) | B41: Limits sign-up confirmation, password links, company approval emails | C41: OAN | D41: Open
A42: Gate G-CH: Slack app, WhatsApp Business number, DPAs, DPIA annex | B42: Gated channels are built but switched off | C42: OAN | D42: Open
A43: Gate G-CF: Oracle Careers feed | B43: Gated Oracle roles are entered as Careers links until then | C43: OAN | D43: Open
A44: PBKDF2 cost (~1.9 s per sign-in at 210k iterations) | B44: Change request: NFR-01 vs login performance | C44: Product owner | D44: Open
A45: Staffing decision (G0) | B45: Open one vs two developers sets the end date | C45: Sponsor | D45: Open
A46: Dev deploy secrets (wallet and passwords) | B46: Deployment to dev stays manual until the owner adds them | C46: OAN | D46: Open
A48: Next steps
A49: - W6: community groups, experts and Ask-the-Expert, mentoring with capacity, training and certificates, partner talent requests and candidate feedback (pages 60-72).
A50: - W7: administration and hardening (pages 100-113), including profile-update and privacy-request admin, library import and channel administration.
A51: - Product-owner demo of W0-W5 once an admin sign-in path is agreed.
A53: Delivery facts
A54: Live board | B54: maheashtiwarrii-dev.github.io/OAN_APP_Portal
A55: Printable board | B55: docs/OAN-Delivery-Board-landscape.pdf
A56: GitHub Project | B56: projects/1 (168 items)
A57: Database objects | B57: 100 tables, 126 secure views, 39 packages
A58: Local release checks | B58: 115 queries and 153 PL/SQL blocks compiled as the app schema; utPLSQL; import to dev
A59: Test data | B59: Synthetic only (Q12): 265 alumni, test accounts, 23 CV-based personas; no Oracle HR documents (Q29, Q35)
A60: Production deployment | B60: Not automated - requires go-live gate 8.0

Sheet Delivered Pages
A1: Delivered Pages on Dev - 73 pages in Application 200
A2: The pages already built and running on the development environment, by area (status report, 15 Oct 2026).
A4: Area | B4: Pages
A5: Sign-in and onboarding | B5: 1 Login - 2 Onboarding - 3 Create account - 4 Access denied - 5 Status - 6 Application - 7 Confirm email - 8 Reset password - 9 Link account - 11 Welcome - 12 Legal - 13 Report a concern - 14 Accept terms - 15 Confirm identity - 44 Unsubscribe
A6: Shell and Home | B6: 0 Global page - 10 Home - 19 Search - 41 Notifications - 42 Notification settings - 43 Slack and WhatsApp
A7: Profile and directory | B7: 20 Directory - 21 Results - 22 Member profile - 23 My profile - 24 My CV - 25 Work profile - 26 Settings - 27 Privacy centre - 28 My network - 29 Help Me Connect - 90 - 91 - 231-234
A8: Insights and events | B8: 30 Insights - 31 Article - 301 Write - 32 Events - 33 Event detail - 331 Event editor - 34-36 Library
A9: Conversations and community | B9: 40 Conversations - 60 Discussions - 62 Post - 73 New post - 80 Report - 81 My decisions
A10: Careers and helpdesk | B10: 50 Opportunities - 51 Opportunity - 52 My applications - 53 Post - 54 Referrals - 55 Helpdesk - 56 Skills in demand
A11: Companies | B11: 76 Register your company (public) - 70 Company workspace - 71 Company opportunities - 112 Company registrations (admin)
A12: Administration (untested) | B12: 101 Members - 106 Taxonomy - 107 Moderation (incl. job review) - 110 Audit - 114 Approvals - 115 Review - 116 Member detail - 117 Chapters - 118 Requests - 119 Appeals
A14: - 73 APEX pages are live on dev; every page is validated with SQLcl before import (offline APEXLang validation).
A15: - Administration pages are built but untested end to end: staff roles need Google or LinkedIn sign-in (NFR-01) and Google sign-in is set aside (Q33).
A16: - Slack and WhatsApp (page 43) are built but switched off until gate G-CH.

Sheet CI-CD Pipeline
A1: CI/CD Pipeline - Build, Validate, Deploy and Publish
A2: Every push and pull request runs the pipeline; deployment to dev is manual and production deployment waits for go-live gate 8.0.
A4: Stage | B4: What runs | C4: State
A5: 1 - Push / pull request | B5: Brand check (no Oracle logos) - Link check (no 404 pages) - Base-table check (NFR-03) - Dev-script guard - Secret scan (gitleaks) | C5: Live
A6: 2 - Build | B6: Offline APEXLang validation with SQLcl (all 73 pages); no database or secrets needed | C6: Live
A7: 3 - Deploy to dev (manual) | B7: Validate again - Import app 200 - Run utPLSQL suites - Smoke-test sign-in page | C7: Live
A8: 4 - Publish | B8: Kanban board, status report and both PDFs to GitHub Pages; GitHub Project kept in step | C8: Live
A10: Pipeline items
A11: Item | B11: Status
A12: Workflows ci.yml, deploy-dev.yml, board.yml | B12: Live - CI green on every push this week
A13: Check scripts (ci/) | B13: Live - links, base tables, brand and validation pass on 73 pages
A14: Board, report and PDFs on GitHub Pages | B14: Live - republished on every push to docs/
A15: Local release checks per iteration | B15: Running - 115 queries and 153 PL/SQL blocks, utPLSQL, import to dev
A16: Dev deploy secrets | B16: Pending - wallet and passwords to be added by the owner in environment dev
A17: Production deployment | B17: Not automated - requires go-live gate 8.0
